source/header.vh
`define ALU_WIDTH 14
`define ADD 0
`define SUB 1
`define SLT 2
`define SLTU 3
`define XOR 4
`define OR 5
`define AND 6
`define SLL 7
`define SRL 8
`define SRA 9
`define EQ 10
`define NEQ 11
`define GE 12
`define GEU 13

`define OPCODE_WIDTH 11
`define RTYPE 0 //Arithmetic operations between two registers
`define ITYPE 1 //Arithmetic operations between one register and immediate value
`define LOAD_WORD 2 //Retrieve data from memory to store in register (rs1 +imm)
`define STORE_WORD 3 //Retrieve data from register to store in memory (rs1 + imm)
`define BRANCH 4 //Branch instruction(pc = pc + 4)
`define JAL 5 //Calculate to jump and store value in target register (pc + imm) 
`define JALR 6 //Calculate target to jump (rs1 + imm)
`define LUI 7 //LUI expect (rd = imm, imm << 12) not rs1 + imm
`define AUIPC 8 //PC + imm is stored in rd 
`define SYSTEM 9 
`define FENCE 10

`define EXCEPTION_WIDTH 4
`define ILLEGAL 0
`define ECALL 1
`define EBREAK 2
`define MRET 3

`define OPCODE_RTYPE 7'b0110011 
`define OPCODE_ITYPE 7'b0010011
`define OPCODE_LOAD 7'b0000011
`define OPCODE_STORE 7'b0100011
`define OPCODE_BRANCH 7'b1100011
`define OPCODE_JAL 7'b1101111
`define OPCODE_JALR 7'b1100111
`define OPCODE_LUI 7'b0110111
`define OPCODE_AUIPC 7'b0010111
`define OPCODE_SYSTEM 7'b1110011
`define OPCODE_FENCE 7'b0001111

`define FUNCT3_ADD 3'b000
`define FUNCT3_SUB 3'b001
`define FUNCT3_SLT 3'b010 
`define FUNCT3_SLTU 3'b011
`define FUNCT3_XOR 3'b100
`define FUNCT3_OR 3'b110
`define FUNCT3_AND 3'b111
`define FUNCT3_SLL 3'b001
`define FUNCT3_SRA 3'b101
`define FUNCT3_EQ 3'b000
`define FUNCT3_NEQ 3'b001
`define FUNCT3_LT 3'b100
`define FUNCT3_GE 3'b101
`define FUNCT3_LTU 3'b110
`define FUNCT3_GEU 3'b111 

`define FUNCT_LB 3'b000 //char 8 bit
`define FUNCT_LH 3'b001 //short 16 bit  
`define FUNCT_LW 3'b010 //int 32 bit
`define FUNCT_LBU 3'b100
`define FUNCT_LHU 3'b101
`define FUNCT_SB 3'b000 //char 8 bit 
`define FUNCT_SH 3'b001 //short 16 bit
`define FUNCT_SW 3'b010 //int 32 bit

source/decoder.v
`ifndef DECODER_V
`define DECODER_V
`include "./source/header.vh"

module decoder #(
    parameter DWIDTH = 32,
    parameter IWIDTH = 32,
    parameter AWIDTH = 5,
    parameter PC_WIDTH = 32,
    parameter FUNCT_WIDTH = 3
)(
    d_clk, d_rst, d_i_instr, d_i_pc, d_o_pc, d_o_addr_rs1, d_o_addr_rs1_p, d_o_addr_rs2, d_o_addr_rs2_p, 
    d_o_addr_rd, d_o_addr_rd_p, d_o_imm, d_o_funct3, d_o_alu, d_o_opcode, d_o_exception, d_i_ce, d_o_ce, 
    d_i_stall, d_o_stall, d_i_flush, d_o_flush
);
    input d_clk, d_rst;
    input [IWIDTH - 1 : 0] d_i_instr;
    input [PC_WIDTH - 1 : 0] d_i_pc;
    output reg [PC_WIDTH - 1 : 0] d_o_pc;
    output [AWIDTH - 1 : 0] d_o_addr_rs1;
    output [AWIDTH - 1 : 0] d_o_addr_rs2;
    output reg [AWIDTH - 1 : 0] d_o_addr_rs1_p;
    output reg [AWIDTH - 1 : 0] d_o_addr_rs2_p;
    output [AWIDTH - 1 : 0] d_o_addr_rd;
    output reg [AWIDTH - 1 : 0] d_o_addr_rd_p;
    output reg [FUNCT_WIDTH - 1 : 0] d_o_funct3;
    output reg [DWIDTH - 1 : 0] d_o_imm;
    output reg [`ALU_WIDTH - 1 : 0] d_o_alu;
    output reg [`OPCODE_WIDTH - 1 : 0] d_o_opcode;
    output reg [`EXCEPTION_WIDTH - 1 : 0] d_o_exception;
    input d_i_ce;
    output reg d_o_ce;
    input d_i_stall;
    output reg d_o_stall;
    input d_i_flush;
    output reg d_o_flush;

    reg [AWIDTH - 1 : 0] temp_addr_rs2, temp_addr_rs1, temp_addr_rd;
    assign d_o_addr_rs2 = temp_addr_rs2;
    assign d_o_addr_rs1 = temp_addr_rs1;
    assign d_o_addr_rd = temp_addr_rd;
    reg [2 : 0] funct3;
    reg [6 : 0] opcode;

    reg [31 : 0] imm_d;
    reg alu_add_d;
    reg alu_sub_d;
    reg alu_slt_d;
    reg alu_sltu_d;
    reg alu_xor_d;
    reg alu_or_d;
    reg alu_and_d;
    reg alu_sll_d;
    reg alu_srl_d;
    reg alu_sra_d;
    reg alu_eq_d;
    reg alu_neq_d;
    reg alu_lt_d;
    reg alu_ltu_d;
    reg alu_ge_d;
    reg alu_geu_d;

    reg opcode_rtype_d;
    reg opcode_itype_d;
    reg opcode_load_word_d;
    reg opcode_store_word_d;
    reg opcode_branch_d;
    reg opcode_jal_d;
    reg opcode_jalr_d;
    reg opcode_lui_d;
    reg opcode_auipc_d;
    reg opcode_system_d;
    reg opcode_fence_d;

    reg valid_opcode;
    reg illegal_check;
    reg system_exeption;
    wire stall_bit = d_o_stall || d_i_stall;

    always @(posedge d_clk, negedge d_rst) begin
        if (!d_rst) begin
            d_o_ce <= 0;
            valid_opcode <= 0;
            illegal_check <= 0;
            system_exeption <= 0;
            temp_addr_rs2 <= {AWIDTH{1'b0}};
            d_o_addr_rs1_p <= {AWIDTH{1'b0}};
            d_o_addr_rs2_p <= {AWIDTH{1'b0}};
            d_o_addr_rd_p <= {AWIDTH{1'b0}};
            temp_addr_rs2 <= {AWIDTH{1'b0}};
            temp_addr_rs1 <= {AWIDTH{1'b0}};
            temp_addr_rd <= {AWIDTH{1'b0}};
        end
        else begin
            if (d_o_ce && !stall_bit) begin
                d_o_pc <= d_i_pc;
                d_o_addr_rs1_p <= temp_addr_rs1;
                d_o_addr_rs2_p <= temp_addr_rs2;
                d_o_addr_rd_p <= temp_addr_rd;
                d_o_funct3 <= funct3;
                d_o_opcode <= opcode;
                d_o_imm <= imm_d;
                
                d_o_alu[`ADD] <= alu_add_d;
                d_o_alu[`SUB] <= alu_sub_d;
                d_o_alu[`SLT] <= alu_slt_d;
                d_o_alu[`SLTU] <= alu_sltu_d;
                d_o_alu[`XOR] <= alu_xor_d;
                d_o_alu[`OR] <= alu_or_d;
                d_o_alu[`AND] <= alu_and_d;
                d_o_alu[`SLL] <= alu_sll_d;
                d_o_alu[`SRL] <= alu_srl_d;
                d_o_alu[`SRA] <= alu_sra_d;
                d_o_alu[`EQ] <= alu_eq_d;
                d_o_alu[`NEQ] <= alu_neq_d;
                d_o_alu[`GE] <= alu_ge_d;
                d_o_alu[`GEU] <= alu_geu_d;

                d_o_opcode[`RTYPE] <= opcode_rtype_d;
                d_o_opcode[`ITYPE] <= opcode_itype_d;
                d_o_opcode[`LOAD] <= opcode_load_word_d;
                d_o_opcode[`STORE] <= opcode_store_word_d;
                d_o_opcode[`BRANCH] <= opcode_branch_d;
                d_o_opcode[`JAL] <= opcode_jal_d;
                d_o_opcode[`JALR] <= opcode_jalr_d;
                d_o_opcode[`LUI] <= opcode_lui_d;
                d_o_opcode[`AUIPC] <= opcode_auipc_d;
                d_o_opcode[`SYSTEM] <= opcode_system_d;
                d_o_opcode[`FENCE] <= opcode_fence_d;
            end

            d_o_opcode <= opcode;
            d_o_exception[`ILLEGAL] <= !valid_opcode || illegal_check;
            d_o_exception[`ECALL] <= (system_exeption && d_i_instr[21 : 20] == 2'b00) ? 1 : 0;
            d_o_exception[`EBREAK] <= (system_exeption && d_i_instr[21 : 20] == 2'b01) ? 1 : 0;
            d_o_exception[`MRET] <= (system_exeption && d_i_instr[21 : 20] == 2'b10) ? 1 : 0;

            if (d_i_flush && !stall_bit) begin
                d_o_ce <= 0;
            end
            else if (!stall_bit) begin
                d_o_ce <= d_i_ce;
            end
            else if (stall_bit && !d_i_stall) begin
                d_o_ce <= 0;
            end
        end
    end

    always@ (*)begin
        temp_addr_rs1 = {AWIDTH{1'b0}};
        temp_addr_rs2 = {AWIDTH{1'b0}};
        temp_addr_rd  = {AWIDTH{1'b0}};
        opcode = d_i_instr[6 : 0];
        funct3        = 3'b0;
        
        opcode_rtype_d = opcode == `OPCODE_RTYPE;
        opcode_itype_d = opcode == `OPCODE_ITYPE;
        opcode_load_word_d = opcode == `OPCODE_LOAD;
        opcode_store_word_d = opcode == `OPCODE_STORE;
        opcode_branch_d = opcode == `OPCODE_BRANCH;
        opcode_jal_d = opcode == `OPCODE_JAL;
        opcode_jalr_d = opcode == `OPCODE_JALR; 
        opcode_lui_d = opcode == `OPCODE_LUI;
        opcode_auipc_d = opcode == `OPCODE_AUIPC;
        opcode_system_d = opcode == `OPCODE_SYSTEM; 
        opcode_fence_d = opcode == `OPCODE_FENCE; 

        system_exeption = opcode == `OPCODE_SYSTEM && funct3 == 0;
        valid_opcode = (opcode_rtype_d || opcode_itype_d || opcode_load_word_d || opcode_store_word_d || opcode_branch_d || opcode_jal_d || opcode_jalr_d || opcode_lui_d || opcode_auipc_d || opcode_system_d || opcode_fence_d);
        illegal_check = (opcode_itype_d && (alu_sll_d || alu_srl_d || alu_sra_d) && d_i_instr[25] == 0);

        if (opcode_rtype_d) begin
            temp_addr_rs2 = d_i_instr[24 : 20];
            temp_addr_rs1 = d_i_instr[19 : 15];
            temp_addr_rd = d_i_instr[11 : 7];
            funct3 = d_i_instr[14 : 12];
        end
        else if (opcode_itype_d || opcode_load_word_d || opcode_jalr_d || opcode_system_d || opcode_fence_d) begin
            temp_addr_rs2 = {AWIDTH{1'bx}};
            temp_addr_rs1 = d_i_instr[19 : 15];
            temp_addr_rd = d_i_instr[11 : 7];
            funct3 = d_i_instr[14 : 12];
        end
        else if (opcode_store_word_d || opcode_branch_d) begin
            temp_addr_rs2 = d_i_instr[24 : 20];
            temp_addr_rs1 = d_i_instr[19 : 15];
            temp_addr_rd = {AWIDTH{1'bx}};
            funct3 = d_i_instr[14 : 12];
        end
        else if (opcode_lui_d || opcode_auipc_d || opcode_jal_d) begin
            temp_addr_rs2 = {AWIDTH{1'bx}};
            temp_addr_rs1 = {AWIDTH{1'bx}};
            temp_addr_rd = d_i_instr[11 : 7];
            funct3 = {AWIDTH{1'bx}};
        end
        else begin
            temp_addr_rs2 = {AWIDTH{1'bx}};
            temp_addr_rs1 = {AWIDTH{1'bx}};
            temp_addr_rd = {AWIDTH{1'bx}};
            opcode = {`OPCODE_WIDTH{1'bx}};
            funct3 = {3{1'bx}};
        end
    end

    always @(*) begin
        d_o_stall = d_i_stall;
        d_o_flush = d_i_flush;
        alu_add_d = 0;
        alu_sub_d = 0;
        alu_slt_d = 0;
        alu_sltu_d = 0;
        alu_xor_d = 0;
        alu_or_d = 0;
        alu_and_d = 0;
        alu_sll_d = 0;
        alu_srl_d = 0;
        alu_sra_d = 0;
        alu_eq_d = 0;
        alu_neq_d = 0;
        alu_lt_d = 0;
        alu_ltu_d = 0;
        alu_ge_d = 0;
        alu_geu_d = 0;

        if (opcode == `OPCODE_RTYPE || opcode == `OPCODE_ITYPE) begin
            if (opcode == `OPCODE_RTYPE) begin
                if (funct3 == `FUNCT3_ADD && d_i_instr[30] == 0) begin
                    alu_add_d = 1;
                end
                else if (funct3 == `FUNCT3_ADD && d_i_instr[30] == 1) begin
                    alu_sub_d = 1;
                end
            end
            else begin
                alu_add_d = funct3 == `FUNCT3_ADD ? 1 : 0;
            end
            alu_slt_d = funct3 == `FUNCT3_SLT ? 1 : 0;
            alu_sltu_d = funct3 == `FUNCT3_SLTU ? 1 : 0;
            alu_xor_d = funct3 == `FUNCT3_XOR ? 1 : 0;
            alu_or_d = funct3 == `FUNCT3_OR ? 1 : 0;
            alu_and_d = funct3 == `FUNCT3_AND ? 1 : 0;
            alu_sll_d = funct3 == `FUNCT3_SLL ? 1 : 0;
            if (funct3 == `FUNCT3_SRA) begin
                if (d_i_instr[30] == 0) begin
                    alu_srl_d = 1;
                end
                else begin
                    alu_sra_d = 1;
                end
            end
        end
        else if (opcode == `OPCODE_BRANCH) begin
            alu_eq_d = funct3 == `FUNCT3_EQ ? 1 : 0;
            alu_neq_d = funct3 == `FUNCT3_NEQ ? 1 : 0;
            alu_lt_d = funct3 == `FUNCT3_LT ? 1 : 0;
            alu_ge_d = funct3 == `FUNCT3_GE ? 1 : 0;
            alu_ltu_d = funct3 == `FUNCT3_LTU ? 1 : 0;
            alu_geu_d = funct3 == `FUNCT3_GEU ? 1 : 0;
        end
        else begin
            alu_add_d = 1;
        end
    end

    always @(*) begin
        imm_d = 0;
        case (opcode)
            `OPCODE_RTYPE : begin
                imm_d = {32{1'bx}};
            end
            `OPCODE_ITYPE, `OPCODE_JALR, `OPCODE_LOAD : begin
                imm_d = {{20{d_i_instr[31]}}, d_i_instr[31 : 20]};
            end
            `OPCODE_STORE : begin
                imm_d = {{20{d_i_instr[31]}}, d_i_instr[31 : 25], d_i_instr[11 : 7]};
            end
            `OPCODE_BRANCH : begin
                imm_d = {{20{d_i_instr[31]}}, d_i_instr[7], d_i_instr[30 : 25], d_i_instr[11 : 8], 1'b0};
            end
            `OPCODE_JAL : begin
                imm_d = {{12{d_i_instr[31]}}, d_i_instr[19 : 12], d_i_instr[20], d_i_instr[30 : 21], 1'b0};
            end
            `OPCODE_LUI, `OPCODE_AUIPC : begin
                imm_d = {d_i_instr[31 : 12], {12{1'b0}}};
            end
            `OPCODE_SYSTEM, `OPCODE_FENCE : begin
                imm_d = {{20{1'b0}}, d_i_instr[31 : 20]};
            end
            default : begin
                imm_d = {32{1'b0}}; 
            end
        endcase
    end
endmodule
`endif

test/tb_decoder.v
`timescale 1ns/1ps
`include "./source/decoder.v"

module tb_decoder;
    // Parameters
    parameter DWIDTH     = 32;
    parameter IWIDTH     = 32;
    parameter AWIDTH     = 5;
    parameter PC_WIDTH   = 32;
    parameter CLK_PERIOD = 10;

    // Signals
    reg  d_clk;
    reg  d_rst;
    reg  [IWIDTH-1:0]     d_i_instr;
    reg  [PC_WIDTH-1:0]   d_i_pc;
    reg  d_i_ce;
    reg  d_i_stall;
    reg  d_i_flush;

    wire [PC_WIDTH-1:0]       d_o_pc;
    wire [AWIDTH-1:0]         d_o_addr_rs1;
    wire [AWIDTH-1:0]         d_o_addr_rs2;
    wire [AWIDTH-1:0]         d_o_addr_rd;
    wire [AWIDTH-1:0]         d_o_addr_rs1_p;
    wire [AWIDTH-1:0]         d_o_addr_rs2_p;
    wire [AWIDTH-1:0]         d_o_addr_rd_p;
    wire [DWIDTH-1:0]         d_o_imm;
    wire [2:0]                d_o_funct3;
    wire [`ALU_WIDTH-1:0]     d_o_alu;
    wire [`OPCODE_WIDTH-1:0]  d_o_opcode;
    wire [`EXCEPTION_WIDTH-1:0] d_o_exception;
    wire                      d_o_ce;
    wire                      d_o_stall;
    wire                      d_o_flush;

    // Instantiate decoder
    decoder #(
        .DWIDTH(DWIDTH),
        .IWIDTH(IWIDTH),
        .AWIDTH(AWIDTH),
        .PC_WIDTH(PC_WIDTH)
    ) uut (
        .d_clk(d_clk),
        .d_rst(d_rst),
        .d_i_instr(d_i_instr),
        .d_i_pc(d_i_pc),
        .d_i_ce(d_i_ce),
        .d_i_stall(d_i_stall),
        .d_i_flush(d_i_flush),
        .d_o_pc(d_o_pc),
        .d_o_addr_rs1(d_o_addr_rs1),
        .d_o_addr_rs2(d_o_addr_rs2),
        .d_o_addr_rd(d_o_addr_rd),
        .d_o_addr_rs1_p(d_o_addr_rs1_p),
        .d_o_addr_rs2_p(d_o_addr_rs2_p),
        .d_o_addr_rd_p(d_o_addr_rd_p),
        .d_o_imm(d_o_imm),
        .d_o_funct3(d_o_funct3),
        .d_o_alu(d_o_alu),
        .d_o_opcode(d_o_opcode),
        .d_o_exception(d_o_exception),
        .d_o_ce(d_o_ce),
        .d_o_stall(d_o_stall),
        .d_o_flush(d_o_flush)
    );

    // Clock generation
    initial begin
        d_clk = 1'b0;
    end
    always #5 d_clk = ~d_clk;

    initial begin
        $dumpfile("./waveform/decoder.vcd");
        $dumpvars(0, tb_decoder);
    end
    // Reset task
    task reset;
        integer i;
        begin
            d_rst = 1'b0;
            for (i = 0; i < 2; i = i + 1) @(posedge d_clk);
            d_rst = 1'b1;
            @(posedge d_clk);
        end
    endtask

    // Test stimulus
    initial begin
        // Initialize
        d_i_instr  = 0;
        d_i_pc     = 0;
        d_i_ce     = 1'b0;
        d_i_stall  = 1'b0;
        d_i_flush  = 1'b0;
        reset;
        d_i_ce = 1'b1;

        // 1) R-type: add x1, x2, x3
        d_i_instr = {7'b0000000, 5'd3, 5'd2, `FUNCT3_ADD, 5'd1, `OPCODE_RTYPE};
        d_i_pc    = 32'd4; #(CLK_PERIOD*2);
        $display("R ADD:   rs1=%0d rs2=%0d rd=%0d alu[%b] opcode=%b", d_o_addr_rs1, d_o_addr_rs2, d_o_addr_rd, d_o_alu, d_o_opcode);

        // 2) R-type: sub x4, x5, x6
        d_i_instr = {7'b0100000, 5'd6, 5'd5, `FUNCT3_ADD, 5'd4, `OPCODE_RTYPE};
        d_i_pc    = 32'd8; #(CLK_PERIOD*2);
        $display("R SUB:   rs1=%0d rs2=%0d rd=%0d alu[%b] opcode=%b", d_o_addr_rs1, d_o_addr_rs2, d_o_addr_rd, d_o_alu, d_o_opcode);

        // 3) I-type: addi x7, x8, 16
        d_i_instr = {12'd16, 5'd8, `FUNCT3_ADD, 5'd7, `OPCODE_ITYPE};
        d_i_pc    = 32'd12; #(CLK_PERIOD*2);
        $display("I ADDI:  rs1=%0d imm=%0d rd=%0d opcode=%b", d_o_addr_rs1, $signed(d_o_imm), d_o_addr_rd, d_o_opcode);

        // 4) Load: lw x9, 4(x10)
        d_i_instr = {12'd4, 5'd10, 3'b010, 5'd9, `OPCODE_LOAD};
        d_i_pc    = 32'd16; #(CLK_PERIOD*2);
        $display("LOAD:    rs1=%0d imm=%0d rd=%0d opcode=%b", d_o_addr_rs1, $signed(d_o_imm), d_o_addr_rd, d_o_opcode);

        // 5) Store: sw x11, 8(x12)
        d_i_instr = {7'b0000000, 5'd11, 5'd12, 3'b010, 5'd8, `OPCODE_STORE};
        d_i_pc    = 32'd20; #(CLK_PERIOD*2);
        $display("STORE:   rs1=%0d rs2=%0d imm=%0d opcode=%b", d_o_addr_rs1, d_o_addr_rs2, $signed(d_o_imm), d_o_opcode);

        // 6) Branch: beq x13, x14, 2
        d_i_instr = {1'b0, 6'b000000, 5'd14, 5'd13, 3'b000, 4'b0010, 1'b0, `OPCODE_BRANCH};
        d_i_pc    = 32'd24; #(CLK_PERIOD*2);
        $display("BRANCH:  rs1=%0d rs2=%0d imm=%0d opcode=%b", d_o_addr_rs1, d_o_addr_rs2, $signed(d_o_imm), d_o_opcode);

        // 7) JAL: jal x15, 16
        d_i_instr = {1'b0, 8'd16, 1'b0, 10'd16, 1'b0, 5'd15, `OPCODE_JAL};
        d_i_pc    = 32'd28; #(CLK_PERIOD*2);
        $display("JAL:     rd=%0d imm=%0d opcode=%b", d_o_addr_rd, $signed(d_o_imm), d_o_opcode);

        // 8) JALR: jalr x16, x17, 20
        d_i_instr = {12'd20, 5'd17, `FUNCT3_ADD, 5'd16, `OPCODE_JALR};
        d_i_pc    = 32'd32; #(CLK_PERIOD*2);
        $display("JALR:    rs1=%0d imm=%0d rd=%0d opcode=%b", d_o_addr_rs1, $signed(d_o_imm), d_o_addr_rd, d_o_opcode);

        // 9) LUI: lui x18, 0x12345
        d_i_instr = {20'h12345, 5'd18, `OPCODE_LUI};
        d_i_pc    = 32'd36; #(CLK_PERIOD*2);
        $display("LUI:     rd=%0d imm=%h opcode=%b", d_o_addr_rd, d_o_imm, d_o_opcode);

        // 10) AUIPC: auipc x19, 0xABCDE
        d_i_instr = {20'hABCDE, 5'd19, `OPCODE_AUIPC};
        d_i_pc    = 32'd40; #(CLK_PERIOD*2);
        $display("AUIPC:   rd=%0d imm=%h opcode=%b", d_o_addr_rd, d_o_imm, d_o_opcode);

        $finish;
    end
endmodule

waveform/decoder.vcd
$date
	Sat Aug 16 00:54:38 2025
$end
$version
	Icarus Verilog
$end
$timescale
	1ps
$end
$scope module tb_decoder $end
$var wire 1 ! d_o_stall $end
$var wire 32 " d_o_pc [31:0] $end
$var wire 11 # d_o_opcode [10:0] $end
$var wire 32 $ d_o_imm [31:0] $end
$var wire 3 % d_o_funct3 [2:0] $end
$var wire 1 & d_o_flush $end
$var wire 4 ' d_o_exception [3:0] $end
$var wire 1 ( d_o_ce $end
$var wire 14 ) d_o_alu [13:0] $end
$var wire 5 * d_o_addr_rs2_p [4:0] $end
$var wire 5 + d_o_addr_rs2 [4:0] $end
$var wire 5 , d_o_addr_rs1_p [4:0] $end
$var wire 5 - d_o_addr_rs1 [4:0] $end
$var wire 5 . d_o_addr_rd_p [4:0] $end
$var wire 5 / d_o_addr_rd [4:0] $end
$var parameter 32 0 AWIDTH $end
$var parameter 32 1 CLK_PERIOD $end
$var parameter 32 2 DWIDTH $end
$var parameter 32 3 IWIDTH $end
$var parameter 32 4 PC_WIDTH $end
$var reg 1 5 d_clk $end
$var reg 1 6 d_i_ce $end
$var reg 1 7 d_i_flush $end
$var reg 32 8 d_i_instr [31:0] $end
$var reg 32 9 d_i_pc [31:0] $end
$var reg 1 : d_i_stall $end
$var reg 1 ; d_rst $end
$scope module uut $end
$var wire 1 5 d_clk $end
$var wire 1 6 d_i_ce $end
$var wire 1 7 d_i_flush $end
$var wire 32 < d_i_instr [31:0] $end
$var wire 32 = d_i_pc [31:0] $end
$var wire 1 : d_i_stall $end
$var wire 5 > d_o_addr_rd [4:0] $end
$var wire 5 ? d_o_addr_rs1 [4:0] $end
$var wire 5 @ d_o_addr_rs2 [4:0] $end
$var wire 1 ; d_rst $end
$var wire 1 A stall_bit $end
$var parameter 32 B AWIDTH $end
$var parameter 32 C DWIDTH $end
$var parameter 32 D FUNCT_WIDTH $end
$var parameter 32 E IWIDTH $end
$var parameter 32 F PC_WIDTH $end
$var reg 1 G alu_add_d $end
$var reg 1 H alu_and_d $end
$var reg 1 I alu_eq_d $end
$var reg 1 J alu_ge_d $end
$var reg 1 K alu_geu_d $end
$var reg 1 L alu_lt_d $end
$var reg 1 M alu_ltu_d $end
$var reg 1 N alu_neq_d $end
$var reg 1 O alu_or_d $end
$var reg 1 P alu_sll_d $end
$var reg 1 Q alu_slt_d $end
$var reg 1 R alu_sltu_d $end
$var reg 1 S alu_sra_d $end
$var reg 1 T alu_srl_d $end
$var reg 1 U alu_sub_d $end
$var reg 1 V alu_xor_d $end
$var reg 5 W d_o_addr_rd_p [4:0] $end
$var reg 5 X d_o_addr_rs1_p [4:0] $end
$var reg 5 Y d_o_addr_rs2_p [4:0] $end
$var reg 14 Z d_o_alu [13:0] $end
$var reg 1 ( d_o_ce $end
$var reg 4 [ d_o_exception [3:0] $end
$var reg 1 & d_o_flush $end
$var reg 3 \ d_o_funct3 [2:0] $end
$var reg 32 ] d_o_imm [31:0] $end
$var reg 11 ^ d_o_opcode [10:0] $end
$var reg 32 _ d_o_pc [31:0] $end
$var reg 1 ! d_o_stall $end
$var reg 3 ` funct3 [2:0] $end
$var reg 1 a illegal_check $end
$var reg 32 b imm_d [31:0] $end
$var reg 7 c opcode [6:0] $end
$var reg 1 d opcode_auipc_d $end
$var reg 1 e opcode_branch_d $end
$var reg 1 f opcode_fence_d $end
$var reg 1 g opcode_itype_d $end
$var reg 1 h opcode_jal_d $end
$var reg 1 i opcode_jalr_d $end
$var reg 1 j opcode_load_word_d $end
$var reg 1 k opcode_lui_d $end
$var reg 1 l opcode_rtype_d $end
$var reg 1 m opcode_store_word_d $end
$var reg 1 n opcode_system_d $end
$var reg 1 o system_exeption $end
$var reg 5 p temp_addr_rd [4:0] $end
$var reg 5 q temp_addr_rs1 [4:0] $end
$var reg 5 r temp_addr_rs2 [4:0] $end
$var reg 1 s valid_opcode $end
$upscope $end
$scope task reset $end
$var integer 32 t i [31:0] $end
$upscope $end
$upscope $end
$enddefinitions $end
$comment Show the parameter values. $end
$dumpall
b100000 F
b100000 E
b11 D
b100000 C
b101 B
b100000 4
b100000 3
b100000 2
b1010 1
b101 0
$end
#0
$dumpvars
b0 t
0s
b0 r
b0 q
b0 p
0o
0n
0m
0l
0k
0j
0i
0h
0g
0f
0e
0d
bx c
b0 b
0a
bx `
bx _
bx ^
bx ]
bx \
bx [
bx Z
b0 Y
b0 X
b0 W
0V
0U
0T
0S
0R
0Q
0P
0O
0N
0M
0L
0K
0J
0I
0H
1G
0A
b0 @
b0 ?
b0 >
b0 =
b0 <
0;
0:
b0 9
b0 8
07
06
05
b0 /
b0 .
b0 -
b0 ,
b0 +
b0 *
bx )
0(
bx '
0&
bx %
bx $
bx #
bx "
0!
$end
#5000
b1 t
15
#10000
05
#15000
b1 '
b1 [
b0xxxxxxx #
b0xxxxxxx ^
1;
b10 t
15
#20000
05
#25000
1(
bx b
1G
b1 /
b1 >
b1 p
b10 -
b10 ?
b10 q
b11 +
b11 @
b11 r
1s
1l
b0 `
b110011 c
b100 9
b100 =
b1100010000000010110011 8
b1100010000000010110011 <
16
15
#30000
05
#35000
b0 '
b0 [
b1 )
b1 Z
b110011 #
b110011 ^
b0 %
b0 \
b1 .
b1 W
b11 *
b11 Y
b10 ,
b10 X
b100 "
b100 _
15
#40000
05
#45000
b110011 #
b110011 ^
b10 )
b10 Z
b100 .
b100 W
b110 *
b110 Y
b101 ,
b101 X
b1000 "
b1000 _
bx b
1U
0G
b100 /
b100 >
b100 p
b110 +
b110 @
b110 r
b101 -
b101 ?
b101 q
15
b1000 9
b1000 =
b1000000011000101000001000110011 8
b1000000011000101000001000110011 <
#50000
05
#55000
b110011 #
b110011 ^
15
#60000
05
#65000
b1 )
b1 Z
b10000 $
b10000 ]
b10011 #
b10011 ^
b111 .
b111 W
bx *
bx Y
b1000 ,
b1000 X
b1100 "
b1100 _
b10000 b
1G
0U
1g
0l
b10011 c
b111 /
b111 >
b111 p
bx +
bx @
bx r
b1000 -
b1000 ?
b1000 q
15
b1100 9
b1100 =
b1000001000000001110010011 8
b1000001000000001110010011 <
#70000
05
#75000
b10011 #
b10011 ^
15
#80000
05
#85000
b100 $
b100 ]
b11 #
b11 ^
b10 %
b10 \
b1001 .
b1001 W
b1010 ,
b1010 X
b10000 "
b10000 _
b100 b
1G
b10 `
1j
0g
b11 c
b1001 /
b1001 >
b1001 p
bx +
bx @
bx r
b1010 -
b1010 ?
b1010 q
15
b10000 9
b10000 =
b10001010010010010000011 8
b10001010010010010000011 <
#90000
05
#95000
b11 #
b11 ^
15
#100000
05
#105000
b1000 $
b1000 ]
b100011 #
b100011 ^
bx .
bx W
b1011 *
b1011 Y
b1100 ,
b1100 X
b10100 "
b10100 _
b1000 b
1G
1m
0j
b10 `
b100011 c
bx /
bx >
bx p
b1011 +
b1011 @
b1011 r
b1100 -
b1100 ?
b1100 q
15
b10100 9
b10100 =
b101101100010010000100011 8
b101101100010010000100011 <
#110000
05
#115000
b100011 #
b100011 ^
15
#120000
05
#125000
b10000000000 )
b10000000000 Z
b100 $
b100 ]
b1100011 #
b1100011 ^
b0 %
b0 \
b1110 *
b1110 Y
b1101 ,
b1101 X
b11000 "
b11000 _
b100 b
1I
0G
1e
0m
b0 `
b1100011 c
bx /
bx >
bx p
b1110 +
b1110 @
b1110 r
b1101 -
b1101 ?
b1101 q
15
b11000 9
b11000 =
b111001101000001001100011 8
b111001101000001001100011 <
#130000
05
#135000
b1100011 #
b1100011 ^
15
#140000
05
#145000
b1 )
b1 Z
b100000000100000000 $
b100000000100000000 ]
b1101111 #
b1101111 ^
bx %
bx \
b1111 .
b1111 W
bx *
bx Y
bx ,
bx X
b11100 "
b11100 _
b100000000100000000 b
1G
0I
bx `
1h
0e
b1101111 c
b1111 /
b1111 >
b1111 p
bx +
bx @
bx r
bx -
bx ?
bx q
15
b11100 9
b11100 =
b10000000000100000011111101111 8
b10000000000100000011111101111 <
#150000
05
#155000
b1101111 #
b1101111 ^
15
#160000
05
#165000
b10100 $
b10100 ]
b1100111 #
b1100111 ^
b0 %
b0 \
b10000 .
b10000 W
b10001 ,
b10001 X
b100000 "
b100000 _
b10100 b
1G
1i
0h
b0 `
b1100111 c
b10000 /
b10000 >
b10000 p
bx +
bx @
bx r
b10001 -
b10001 ?
b10001 q
15
b100000 9
b100000 =
b1010010001000100001100111 8
b1010010001000100001100111 <
#170000
05
#175000
b1100111 #
b1100111 ^
15
#180000
05
#185000
b10010001101000101000000000000 $
b10010001101000101000000000000 ]
b110111 #
b110111 ^
bx %
bx \
b10010 .
b10010 W
bx ,
bx X
b100100 "
b100100 _
b10010001101000101000000000000 b
1G
bx `
1k
0i
b110111 c
b10010 /
b10010 >
b10010 p
bx +
bx @
bx r
bx -
bx ?
bx q
15
b100100 9
b100100 =
b10010001101000101100100110111 8
b10010001101000101100100110111 <
#190000
05
#195000
b110111 #
b110111 ^
15
#200000
05
#205000
b10101011110011011110000000000000 $
b10101011110011011110000000000000 ]
b10111 #
b10111 ^
b10011 .
b10011 W
b101000 "
b101000 _
b10101011110011011110000000000000 b
1G
1d
0k
bx `
b10111 c
b10011 /
b10011 >
b10011 p
bx +
bx @
bx r
bx -
bx ?
bx q
15
b101000 9
b101000 =
b10101011110011011110100110010111 8
b10101011110011011110100110010111 <
#210000
05
#215000
b10111 #
b10111 ^
15
#220000
05
#225000
b10111 #
b10111 ^
15
