source/header.vh
`define ALU_WIDTH 14
`define ADD 0
`define SUB 1
`define SLT 2
`define SLTU 3
`define XOR 4
`define OR 5
`define AND 6
`define SLL 7
`define SRL 8
`define SRA 9
`define EQ 10
`define NEQ 11
`define GE 12
`define GEU 13

`define OPCODE_WIDTH 11
`define RTYPE 0 //Arithmetic operations between two registers
`define ITYPE 1 //Arithmetic operations between one register and immediate value
`define LOAD_WORD 2 //Retrieve data from memory to store in register (rs1 +imm)
`define STORE_WORD 3 //Retrieve data from register to store in memory (rs1 + imm)
`define BRANCH 4 //Branch instruction(pc = pc + 4)
`define JAL 5 //Calculate to jump and store value in target register (pc + imm) 
`define JALR 6 //Calculate target to jump (rs1 + imm)
`define LUI 7 //LUI expect (rd = imm, imm << 12) not rs1 + imm
`define AUIPC 8 //PC + imm is stored in rd 
`define SYSTEM 9 
`define FENCE 10

`define EXCEPTION_WIDTH 4
`define ILLEGAL 0
`define ECALL 1
`define EBREAK 2
`define MRET 3

`define OPCODE_RTYPE 7'b0110011 
`define OPCODE_ITYPE 7'b0010011
`define OPCODE_LOAD 7'b0000011
`define OPCODE_STORE 7'b0100011
`define OPCODE_BRANCH 7'b1100011
`define OPCODE_JAL 7'b1101111
`define OPCODE_JALR 7'b1100111
`define OPCODE_LUI 7'b0110111
`define OPCODE_AUIPC 7'b0010111
`define OPCODE_SYSTEM 7'b1110011
`define OPCODE_FENCE 7'b0001111

`define FUNCT3_ADD 3'b000
`define FUNCT3_SUB 3'b001
`define FUNCT3_SLT 3'b010 
`define FUNCT3_SLTU 3'b011
`define FUNCT3_XOR 3'b100
`define FUNCT3_OR 3'b110
`define FUNCT3_AND 3'b111
`define FUNCT3_SLL 3'b001
`define FUNCT3_SRA 3'b101
`define FUNCT3_EQ 3'b000
`define FUNCT3_NEQ 3'b001
`define FUNCT3_LT 3'b100
`define FUNCT3_GE 3'b101
`define FUNCT3_LTU 3'b110
`define FUNCT3_GEU 3'b111 

`define FUNCT_LB 3'b000 //char 8 bit
`define FUNCT_LH 3'b001 //short 16 bit  
`define FUNCT_LW 3'b010 //int 32 bit
`define FUNCT_LBU 3'b100
`define FUNCT_LHU 3'b101
`define FUNCT_SB 3'b000 //char 8 bit 
`define FUNCT_SH 3'b001 //short 16 bit
`define FUNCT_SW 3'b010 //int 32 bit

source/execute_stage.v
`ifndef EXECUTE_STAGE_V
`define EXECUTE_STAGE_V
`include "./source/header.vh"
module execute #(
    parameter AWIDTH = 5,
    parameter DWIDTH = 32,
    parameter FUNCT_WIDTH = 3,
    parameter PC_WIDTH = 32
)(
    ex_clk, ex_rst, ex_i_alu, ex_i_opcode, ex_o_alu, ex_o_opcode, ex_i_addr_rs1, 
    ex_i_addr_rs2, ex_i_addr_rd, ex_i_data_rs1, ex_i_data_rs2, ex_o_data_rd, 
    ex_i_funct3, ex_o_funct3, ex_i_imm, ex_o_imm, ex_i_ce, ex_o_ce, ex_i_stall, 
    ex_o_stall, ex_i_flush, ex_o_flush, ex_i_pc, ex_o_pc, ex_next_pc, ex_o_change_pc,
    ex_o_we_reg, ex_o_valid, ex_stall_from_alu, ex_o_alu_value, ex_o_addr_rd, ex_o_addr_rs1,
    ex_o_addr_rs2, ex_o_data_rs1, ex_o_data_rs2
);
    input ex_clk, ex_rst;
    // ALU control
    input [`ALU_WIDTH - 1 : 0] ex_i_alu;
    output reg [`ALU_WIDTH - 1 : 0] ex_o_alu;
    wire alu_add = (ex_i_alu == `ADD) ? 1 : 0;
    wire alu_sub = (ex_i_alu == `SUB) ? 1 : 0;
    wire alu_slt = (ex_i_alu == `SLT) ? 1 : 0;
    wire alu_sltu = (ex_i_alu == `SLTU) ? 1 : 0;
    wire alu_xor = (ex_i_alu == `XOR) ? 1 : 0;
    wire alu_or = (ex_i_alu == `OR) ? 1 : 0;
    wire alu_and = (ex_i_alu == `AND) ? 1 : 0;
    wire alu_sll = (ex_i_alu == `SLL) ? 1 : 0;
    wire alu_srl = (ex_i_alu == `SRL) ? 1 : 0;
    wire alu_sra = (ex_i_alu == `SRA) ? 1 : 0;
    wire alu_eq = (ex_i_alu == `EQ) ? 1 : 0;
    wire alu_neq = (ex_i_alu == `NEQ) ? 1 : 0;
    wire alu_ge = (ex_i_alu == `GE) ? 1 : 0;
    wire alu_geu = (ex_i_alu == `GEU) ? 1 : 0;

    // OPCODE control
    input [`OPCODE_WIDTH - 1 : 0] ex_i_opcode;
    output reg [`OPCODE_WIDTH - 1 : 0] ex_o_opcode;
    wire op_rtype = (ex_i_opcode == `RTYPE) ? 1 : 0;
    wire op_itype = (ex_i_opcode == `ITYPE) ? 1 : 0;
    wire op_load = (ex_i_opcode == `LOAD_WORD) ? 1 : 0;
    wire op_store = (ex_i_opcode == `STORE_WORD) ? 1 : 0;
    wire op_branch = (ex_i_opcode == `BRANCH) ? 1 : 0;
    wire op_jal = (ex_i_opcode == `JAL) ? 1 : 0;
    wire op_jalr = (ex_i_opcode == `JALR) ? 1 : 0;
    wire op_lui = (ex_i_opcode == `LUI) ? 1 : 0;
    wire op_auipc = (ex_i_opcode == `AUIPC) ? 1 : 0;
    wire op_system = (ex_i_opcode == `SYSTEM) ? 1 : 0;
    wire op_fence = (ex_i_opcode == `FENCE) ? 1 : 0;

    //Register rs1, rs2, rd
    input [AWIDTH - 1 : 0] ex_i_addr_rs1;
    output reg [AWIDTH - 1 : 0] ex_o_addr_rs1;
    input [AWIDTH - 1 : 0] ex_i_addr_rs2;
    output reg [AWIDTH - 1 : 0] ex_o_addr_rs2;
    input [AWIDTH - 1 : 0] ex_i_addr_rd;
    input [DWIDTH - 1 : 0] ex_i_data_rs1;
    output reg [DWIDTH - 1 : 0] ex_o_data_rs1;
    input [DWIDTH - 1 : 0] ex_i_data_rs2;
    output reg [DWIDTH - 1 : 0] ex_o_data_rs2;
    output reg [AWIDTH - 1 : 0] ex_o_addr_rd;
    output reg [DWIDTH - 1 : 0] ex_o_data_rd;
    output reg [DWIDTH - 1 : 0] ex_o_alu_value;
    output reg ex_o_valid;

    //PC
    input [PC_WIDTH - 1 : 0] ex_i_pc;
    output reg [PC_WIDTH - 1 : 0] ex_o_pc;
    output reg [PC_WIDTH - 1 : 0] ex_next_pc;
    output reg ex_o_change_pc;

    //The remaining components
    input [FUNCT_WIDTH - 1 : 0] ex_i_funct3;
    output reg [FUNCT_WIDTH - 1 : 0] ex_o_funct3;
    input [DWIDTH - 1 : 0] ex_i_imm;
    output reg [DWIDTH - 1 : 0] ex_o_imm;
    output reg ex_o_we_reg;
    
    //Enable, stall, flush pipeline
    input ex_i_ce;
    output reg ex_o_ce;
    input ex_i_stall;
    output reg ex_o_stall;
    input ex_i_flush;
    output reg ex_o_flush;
    output reg ex_stall_from_alu;

    //Temporary variables
    reg [DWIDTH - 1 : 0] alu_value;
    wire [PC_WIDTH - 1 : 0] temp_pc;
    assign temp_pc = ex_i_pc;
    reg [DWIDTH - 1 : 0] a, b;
    wire [4 : 0] shamt = b[4 : 0];
    wire next_stall = (op_load || op_store) && ex_i_ce;
    wire stall_bit = ex_i_stall || next_stall;
    reg [DWIDTH - 1 : 0] temp_data_rd;
    //Forwarding value avoids using old data when writeback occurs in the same cycle as decoder/execute read
    wire [DWIDTH - 1 : 0] rs1_value = (ex_o_we_reg && (ex_i_addr_rd == ex_i_addr_rs1)) ? temp_data_rd : ex_i_data_rs1;
    wire [DWIDTH - 1 : 0] rs2_value = (ex_o_we_reg && (ex_i_addr_rd == ex_i_addr_rs2)) ? temp_data_rd : ex_i_data_rs2;

    always @(posedge ex_clk, negedge ex_rst) begin
        if (!ex_rst) begin
            ex_o_valid <= 1'b0;
            ex_o_flush <= 1'b0;
            ex_o_stall <= 1'b0;
            ex_o_we_reg <= 1'b0;
            ex_o_change_pc <= 1'b0;
            ex_stall_from_alu <= 1'b0;
            ex_o_imm <= {DWIDTH{1'b0}};
            ex_o_pc <= {PC_WIDTH{1'b0}};
            ex_next_pc <= {PC_WIDTH{1'b0}};
            ex_o_data_rd <= {DWIDTH{1'b0}};
            ex_o_addr_rd <= {AWIDTH{1'b0}};
            ex_o_data_rs2 <= {DWIDTH{1'b0}};
            ex_o_data_rs1 <= {DWIDTH{1'b0}};
            ex_o_alu <= {`ALU_WIDTH{1'b0}};
            temp_data_rd <= {DWIDTH{1'b0}};
            ex_o_addr_rs2 <= {AWIDTH{1'b0}};
            ex_o_addr_rs1 <= {AWIDTH{1'b0}};
            ex_o_funct3 <= {FUNCT_WIDTH{1'b0}};
            ex_o_opcode <= {`OPCODE_WIDTH{1'b0}};
        end
        else begin
            ex_next_pc        <= temp_pc;
            ex_o_pc           <= temp_pc;
            ex_o_addr_rd      <= ex_i_addr_rd; 
            ex_o_data_rd      <= {DWIDTH{1'b0}};
            // default/clear per-cycle values (prevents stale outputs)
            ex_o_flush        <= 1'b0;
            ex_o_change_pc    <= 1'b0;
            ex_o_we_reg       <= 1'b0;
            ex_o_valid        <= 1'b0;
            ex_stall_from_alu <= 1'b0;
            ex_o_stall        <= 1'b0; // registered stall flag (sampled)
            ex_o_ce           <= 1'b0;
            ex_o_alu          <= {`ALU_WIDTH{1'b0}};
            ex_o_opcode       <= {`OPCODE_WIDTH{1'b0}};
            ex_o_funct3       <= {FUNCT_WIDTH{1'b0}};
            temp_data_rd      <= {DWIDTH{1'b0}};

            if (!ex_i_flush) begin
                if (ex_i_ce && !stall_bit) begin
                    ex_o_alu <= ex_i_alu;
                    ex_o_opcode <= ex_i_opcode;
                    ex_o_funct3 <= ex_i_funct3;
                    ex_o_addr_rs1 <= ex_i_addr_rs1;
                    ex_o_addr_rs2 <= ex_i_addr_rs2;
                    ex_o_data_rs1 <= ex_i_data_rs1;
                    ex_o_data_rs2 <= ex_i_data_rs2;
                    ex_o_imm <= ex_i_imm;
                    ex_stall_from_alu <= (op_load || op_store) ? 1 : 0;
                    ex_o_alu_value <= alu_value;
                    ex_o_stall <= (op_load || op_store) ? 1 : 0;
                    ex_o_data_rd <= temp_data_rd;
                    
                    if (op_rtype || op_itype) begin
                        temp_data_rd <= alu_value;
                        ex_o_valid <= 1'b1;
                        ex_o_we_reg <= 1'b1;
                    end
                    else if (op_branch) begin
                        if (alu_value[0]) begin //Bit 0 is value of the comparison
                            ex_next_pc <= temp_pc + ex_i_imm;
                            ex_o_change_pc <= ex_i_ce;
                            ex_o_flush <= ex_i_ce;
                        end
                        else begin
                            ex_next_pc <= temp_pc + 32'd4;
                            ex_o_change_pc <= 1'b0;
                            ex_o_flush <= 1'b0;
                        end
                    end
                    else if (op_jal) begin
                        ex_next_pc <= temp_pc + ex_i_imm;
                        ex_o_change_pc <= ex_i_ce;
                        ex_o_flush <= ex_i_ce;
                        ex_o_we_reg <= 1'b1;
                        temp_data_rd <= temp_pc + 4;
                        ex_o_valid <= 1'b1;
                    end
                    else if (op_jalr) begin
                        ex_next_pc <= (ex_i_data_rs1 + ex_i_imm) & ~32'h1;
                        ex_o_change_pc <= ex_i_ce;
                        ex_o_flush <= ex_i_ce;
                        ex_o_we_reg <= 1'b1;
                        temp_data_rd <= temp_pc + 4;
                        ex_o_valid <= 1'b1;
                    end
                    else if (op_lui) begin
                        ex_o_change_pc <= 1'b0;
                        ex_o_flush <= 1'b0;
                        ex_o_we_reg <= 1'b1;
                        temp_data_rd <= ex_i_imm[31 : 12] << 12;
                        ex_o_valid <= 1'b1;
                    end
                    else if (op_auipc) begin
                        ex_o_change_pc <= 1'b0;
                        ex_o_flush <= 1'b0;
                        ex_o_we_reg <= 1'b1;
                        temp_data_rd <= ex_i_pc + ex_i_imm;
                        ex_o_valid <= 1'b1;
                    end
                    else begin
                        ex_o_change_pc <= 1'b0;
                        ex_o_flush <= 1'b0;
                        ex_o_valid <= 1'b0;
                        ex_o_we_reg <= 1'b0;
                        temp_data_rd <= {DWIDTH{1'b0}};
                    end
                end
            end
            //Control next stage enable
            if (ex_i_flush && !stall_bit) begin
                ex_o_ce <= 0;
            end
            else if (!stall_bit) begin
                ex_o_ce <= ex_i_ce;
            end
            else if (stall_bit && !ex_i_stall) begin
                ex_o_ce <= 0;
            end
        end
    end

    always @(*) begin
        a = (op_jal || op_auipc) ? ex_i_pc : op_lui ? {DWIDTH{1'b0}} : rs1_value;
        b = (op_rtype || op_branch) ? rs2_value : ex_i_imm;
        alu_value = {DWIDTH{1'b0}};

        if (alu_add) begin
            alu_value = a + b;
        end
        else if (alu_sub) begin
            alu_value = a - b;
        end
        else if (alu_slt) begin
            if ($signed (a) < $signed(b)) begin
                alu_value = {31'b0, 1'b1};
            end
            else begin
                alu_value = 32'b0;
            end
        end
        else if (alu_sltu) begin
            if ($unsigned (a) < $unsigned(b)) begin
                alu_value = {31'b0, 1'b1};
            end
            else begin
                alu_value = 32'b0;
            end
        end
        else if (alu_xor) begin
            alu_value = a ^ b;
        end
        else if (alu_or) begin
            alu_value = a | b;
        end
        else if (alu_and) begin
            alu_value = a & b;
        end
        else if (alu_sll) begin
            alu_value = a << shamt;
        end
        else if (alu_srl) begin
            alu_value = a >> shamt;
        end
        else if (alu_sra) begin
            alu_value = $signed(a) >>> shamt;
        end
        else if (alu_eq) begin
            alu_value = (a == b) ? 32'd1 : 32'd0;
        end
        else if (alu_neq) begin
            alu_value = (a == b) ? 32'd0 : 32'd1;
        end
        else if (alu_ge) begin
            if ($signed (a) >= $signed(b)) begin
                alu_value = {31'b0, 1'b1};
            end
            else begin
                alu_value = 32'b0;
            end
        end
        else if (alu_geu) begin
            if ($unsigned (a) >= $unsigned(b)) begin
                alu_value = {31'b0, 1'b1};
            end
            else begin
                alu_value = 32'b0;
            end
        end
    end
endmodule
`endif

test/tb_execute_stage.v
`include "./source/execute_stage.v"
module tb;
    parameter AWIDTH = 5;
    parameter DWIDTH = 32;
    parameter FUNCT_WIDTH = 3;
    parameter PC_WIDTH = 32;

    reg ex_clk, ex_rst;
    reg [`ALU_WIDTH - 1 : 0] ex_i_alu;
    reg [`OPCODE_WIDTH - 1 : 0] ex_i_opcode;
    wire [`ALU_WIDTH - 1 : 0] ex_o_alu;
    wire [`OPCODE_WIDTH - 1 : 0] ex_o_opcode;
    reg [AWIDTH - 1 : 0] ex_i_addr_rs1;
    wire [AWIDTH - 1 : 0] ex_o_addr_rs1;
    reg [AWIDTH - 1 : 0] ex_i_addr_rs2;
    wire [AWIDTH - 1 : 0] ex_o_addr_rs2;
    reg [AWIDTH - 1 : 0] ex_i_addr_rd;
    wire [AWIDTH - 1 : 0] ex_o_addr_rd;
    reg [DWIDTH - 1 : 0] ex_i_data_rs1;
    wire [DWIDTH - 1 : 0] ex_o_data_rs1;
    reg [DWIDTH - 1 : 0] ex_i_data_rs2;
    wire [DWIDTH - 1 : 0] ex_o_data_rs2;
    wire [DWIDTH - 1 : 0] ex_o_data_rd; 
    wire [DWIDTH - 1 : 0] ex_o_alu_value;
    reg [FUNCT_WIDTH - 1 : 0] ex_i_funct3; 
    wire [FUNCT_WIDTH - 1 : 0] ex_o_funct3;
    reg [DWIDTH - 1 : 0] ex_i_imm; 
    wire [DWIDTH - 1 : 0] ex_o_imm;
    reg ex_i_ce;
    wire ex_o_ce;
    reg ex_i_stall;
    wire ex_o_stall; 
    reg ex_i_flush;
    wire ex_o_flush;
    reg [PC_WIDTH - 1 : 0] ex_i_pc;
    wire [PC_WIDTH - 1 : 0] ex_o_pc;
    wire [PC_WIDTH - 1 : 0] ex_next_pc;
    wire ex_o_change_pc;
    wire ex_o_we_reg; 
    wire ex_o_valid;
    wire ex_stall_from_alu;

    execute #(
        .AWIDTH(AWIDTH),
        .DWIDTH(DWIDTH),
        .PC_WIDTH(PC_WIDTH),
        .FUNCT_WIDTH(FUNCT_WIDTH)
    ) e (
        .ex_clk(ex_clk), 
        .ex_rst(ex_rst), 
        .ex_i_alu(ex_i_alu), 
        .ex_i_opcode(ex_i_opcode), 
        .ex_o_alu(ex_o_alu), 
        .ex_o_opcode(ex_o_opcode),
        .ex_i_addr_rs1(ex_i_addr_rs1), 
        .ex_o_addr_rs1(ex_o_addr_rs1),
        .ex_i_addr_rs2(ex_i_addr_rs2),
        .ex_o_addr_rs2(ex_o_addr_rs2), 
        .ex_i_addr_rd(ex_i_addr_rd), 
        .ex_i_data_rs1(ex_i_data_rs1), 
        .ex_o_data_rs1(ex_o_data_rs1),
        .ex_i_data_rs2(ex_i_data_rs2),
        .ex_o_data_rs2(ex_o_data_rs2), 
        .ex_o_data_rd(ex_o_data_rd), 
        .ex_i_funct3(ex_i_funct3), 
        .ex_o_funct3(ex_o_funct3), 
        .ex_i_imm(ex_i_imm), 
        .ex_o_imm(ex_o_imm), 
        .ex_i_ce(ex_i_ce), 
        .ex_o_ce(ex_o_ce), 
        .ex_i_stall(ex_i_stall), 
        .ex_o_stall(ex_o_stall), 
        .ex_i_flush(ex_i_flush), 
        .ex_o_flush(ex_o_flush), 
        .ex_i_pc(ex_i_pc), 
        .ex_o_pc(ex_o_pc), 
        .ex_next_pc(ex_next_pc), 
        .ex_o_change_pc(ex_o_change_pc),
        .ex_o_we_reg(ex_o_we_reg), 
        .ex_o_valid(ex_o_valid), 
        .ex_stall_from_alu(ex_stall_from_alu),
        .ex_o_addr_rd(ex_o_addr_rd),
        .ex_o_alu_value(ex_o_alu_value)
    );

    initial begin
        $dumpfile("./waveform/execute_stage.vcd");
        $dumpvars(0, tb);
    end
    // Clock generation
    initial begin
        ex_clk = 0;
    end
    always #5 ex_clk = ~ex_clk;

    task reset();
        begin
            ex_rst = 0;
            ex_i_ce = 0;
            ex_i_stall = 0;
            ex_i_flush = 0;
            #10;
            ex_rst = 1;
            #10;
        end
    endtask

    task test_instruction(
        input [`ALU_WIDTH-1:0] alu,
        input [`OPCODE_WIDTH-1:0] opcode,
        input [DWIDTH-1:0] rs1,
        input [DWIDTH-1:0] rs2,
        input [DWIDTH-1:0] imm,
        input [PC_WIDTH-1:0] pc
    );
        begin
            ex_i_alu = alu;
            ex_i_opcode = opcode;
            ex_i_data_rs1 = rs1;
            ex_i_data_rs2 = rs2;
            ex_i_imm = imm;
            ex_i_pc = pc;
            ex_i_ce = 1;
            ex_i_flush = 0;
            ex_i_stall = 0;
            ex_i_addr_rs1 = 5'd1;
            ex_i_addr_rs2 = 5'd2;
            ex_i_addr_rd  = 5'd3;
            @(posedge ex_clk);
            #1;
            $display("Time = %0d", $time);
            $display("NextPC: ex_next_pc = 0x%h", ex_next_pc);
            $display("rs1 = %d, rs2 = %d", ex_o_data_rs1, ex_o_data_rs2);
            $display("Alu value : ex_o_alu_value = 0x%h", ex_o_alu_value);
            $display("Result: ex_o_data_rd = 0x%h", ex_o_data_rd);
            $display("ChangePC: %b, WE: %b, Valid: %b, Stall = %b, Ce = %b\n",
                     ex_o_change_pc, ex_o_we_reg, ex_o_valid, ex_o_stall, ex_o_ce);
        end
    endtask

    initial begin
        reset();

        // ADD: 10 + 20
        test_instruction(`ADD, `RTYPE, 32'd10, 32'd20, 32'd0, 32'h1000);

        // SUB: 50 - 30
        test_instruction(`SUB, `RTYPE, 32'd50, 32'd30, 32'd0, 32'h1004);

        // SLL: 1 << 3 = 8
        test_instruction(`SLL, `RTYPE, 32'd1, 32'd3, 32'd0, 32'h1008);

        // SRA: signed(-16) >>> 2 = -4
        test_instruction(`SRA, `RTYPE, -32'd16, 32'd2, 32'd0, 32'h100C);

        // LUI: imm = 0xABCD000
        test_instruction(`ADD, `LUI, 32'd0, 32'd0, 32'hABCD1234, 32'h1010);

        // AUIPC: pc + imm
        test_instruction(`ADD, `AUIPC, 32'd0, 32'd0, 32'h100, 32'h2000);

        // JAL: pc + imm, rd = pc + 4
        test_instruction(`ADD, `JAL, 32'd0, 32'd0, 32'h10, 32'h3000);

        // BRANCH: (10 == 10) => jump
        test_instruction(`EQ, `BRANCH, 32'd10, 32'd10, 32'h4, 32'h4000);

        // Done
        #20;
        $finish;
    end

endmodule

waveform/execute_stage.vcd
$date
	Sat Sep 06 15:36:40 2025
$end
$version
	Icarus Verilog
$end
$timescale
	1s
$end
$scope module tb $end
$var wire 1 ! ex_stall_from_alu $end
$var wire 1 " ex_o_we_reg $end
$var wire 1 # ex_o_valid $end
$var wire 1 $ ex_o_stall $end
$var wire 32 % ex_o_pc [31:0] $end
$var wire 11 & ex_o_opcode [10:0] $end
$var wire 32 ' ex_o_imm [31:0] $end
$var wire 3 ( ex_o_funct3 [2:0] $end
$var wire 1 ) ex_o_flush $end
$var wire 32 * ex_o_data_rs2 [31:0] $end
$var wire 32 + ex_o_data_rs1 [31:0] $end
$var wire 32 , ex_o_data_rd [31:0] $end
$var wire 1 - ex_o_change_pc $end
$var wire 1 . ex_o_ce $end
$var wire 32 / ex_o_alu_value [31:0] $end
$var wire 14 0 ex_o_alu [13:0] $end
$var wire 5 1 ex_o_addr_rs2 [4:0] $end
$var wire 5 2 ex_o_addr_rs1 [4:0] $end
$var wire 5 3 ex_o_addr_rd [4:0] $end
$var wire 32 4 ex_next_pc [31:0] $end
$var parameter 32 5 AWIDTH $end
$var parameter 32 6 DWIDTH $end
$var parameter 32 7 FUNCT_WIDTH $end
$var parameter 32 8 PC_WIDTH $end
$var reg 1 9 ex_clk $end
$var reg 5 : ex_i_addr_rd [4:0] $end
$var reg 5 ; ex_i_addr_rs1 [4:0] $end
$var reg 5 < ex_i_addr_rs2 [4:0] $end
$var reg 14 = ex_i_alu [13:0] $end
$var reg 1 > ex_i_ce $end
$var reg 32 ? ex_i_data_rs1 [31:0] $end
$var reg 32 @ ex_i_data_rs2 [31:0] $end
$var reg 1 A ex_i_flush $end
$var reg 3 B ex_i_funct3 [2:0] $end
$var reg 32 C ex_i_imm [31:0] $end
$var reg 11 D ex_i_opcode [10:0] $end
$var reg 32 E ex_i_pc [31:0] $end
$var reg 1 F ex_i_stall $end
$var reg 1 G ex_rst $end
$scope module e $end
$var wire 1 9 ex_clk $end
$var wire 5 H ex_i_addr_rd [4:0] $end
$var wire 5 I ex_i_addr_rs1 [4:0] $end
$var wire 5 J ex_i_addr_rs2 [4:0] $end
$var wire 14 K ex_i_alu [13:0] $end
$var wire 1 > ex_i_ce $end
$var wire 32 L ex_i_data_rs1 [31:0] $end
$var wire 32 M ex_i_data_rs2 [31:0] $end
$var wire 1 A ex_i_flush $end
$var wire 3 N ex_i_funct3 [2:0] $end
$var wire 32 O ex_i_imm [31:0] $end
$var wire 11 P ex_i_opcode [10:0] $end
$var wire 32 Q ex_i_pc [31:0] $end
$var wire 1 F ex_i_stall $end
$var wire 1 G ex_rst $end
$var wire 1 R next_stall $end
$var wire 1 S stall_bit $end
$var wire 32 T temp_pc [31:0] $end
$var wire 5 U shamt [4:0] $end
$var wire 32 V rs2_value [31:0] $end
$var wire 32 W rs1_value [31:0] $end
$var wire 1 X op_system $end
$var wire 1 Y op_store $end
$var wire 1 Z op_rtype $end
$var wire 1 [ op_lui $end
$var wire 1 \ op_load $end
$var wire 1 ] op_jalr $end
$var wire 1 ^ op_jal $end
$var wire 1 _ op_itype $end
$var wire 1 ` op_fence $end
$var wire 1 a op_branch $end
$var wire 1 b op_auipc $end
$var wire 1 c alu_xor $end
$var wire 1 d alu_sub $end
$var wire 1 e alu_srl $end
$var wire 1 f alu_sra $end
$var wire 1 g alu_sltu $end
$var wire 1 h alu_slt $end
$var wire 1 i alu_sll $end
$var wire 1 j alu_or $end
$var wire 1 k alu_neq $end
$var wire 1 l alu_geu $end
$var wire 1 m alu_ge $end
$var wire 1 n alu_eq $end
$var wire 1 o alu_and $end
$var wire 1 p alu_add $end
$var parameter 32 q AWIDTH $end
$var parameter 32 r DWIDTH $end
$var parameter 32 s FUNCT_WIDTH $end
$var parameter 32 t PC_WIDTH $end
$var reg 32 u a [31:0] $end
$var reg 32 v alu_value [31:0] $end
$var reg 32 w b [31:0] $end
$var reg 32 x ex_next_pc [31:0] $end
$var reg 5 y ex_o_addr_rd [4:0] $end
$var reg 5 z ex_o_addr_rs1 [4:0] $end
$var reg 5 { ex_o_addr_rs2 [4:0] $end
$var reg 14 | ex_o_alu [13:0] $end
$var reg 32 } ex_o_alu_value [31:0] $end
$var reg 1 . ex_o_ce $end
$var reg 1 - ex_o_change_pc $end
$var reg 32 ~ ex_o_data_rd [31:0] $end
$var reg 32 !" ex_o_data_rs1 [31:0] $end
$var reg 32 "" ex_o_data_rs2 [31:0] $end
$var reg 1 ) ex_o_flush $end
$var reg 3 #" ex_o_funct3 [2:0] $end
$var reg 32 $" ex_o_imm [31:0] $end
$var reg 11 %" ex_o_opcode [10:0] $end
$var reg 32 &" ex_o_pc [31:0] $end
$var reg 1 $ ex_o_stall $end
$var reg 1 # ex_o_valid $end
$var reg 1 " ex_o_we_reg $end
$var reg 1 ! ex_stall_from_alu $end
$var reg 32 '" temp_data_rd [31:0] $end
$upscope $end
$scope task reset $end
$upscope $end
$scope task test_instruction $end
$var reg 14 (" alu [13:0] $end
$var reg 32 )" imm [31:0] $end
$var reg 11 *" opcode [10:0] $end
$var reg 32 +" pc [31:0] $end
$var reg 32 ," rs1 [31:0] $end
$var reg 32 -" rs2 [31:0] $end
$upscope $end
$upscope $end
$enddefinitions $end
$comment Show the parameter values. $end
$dumpall
b100000 t
b11 s
b100000 r
b101 q
b100000 8
b11 7
b100000 6
b101 5
$end
#0
$dumpvars
bx -"
bx ,"
bx +"
bx *"
bx )"
bx ("
b0 '"
b0 &"
b0 %"
b0 $"
b0 #"
b0 ""
b0 !"
b0 ~
bx }
b0 |
b0 {
b0 z
b0 y
b0 x
bx w
b0 v
bx u
xp
xo
xn
xm
xl
xk
xj
xi
xh
xg
xf
xe
xd
xc
xb
xa
x`
x_
x^
x]
x\
x[
xZ
xY
xX
bx W
bx V
bx U
bx T
0S
0R
bx Q
bx P
bx O
bx N
bx M
bx L
bx K
bx J
bx I
bx H
0G
0F
bx E
bx D
bx C
bx B
0A
bx @
bx ?
0>
bx =
bx <
bx ;
bx :
09
b0 4
b0 3
b0 2
b0 1
b0 0
bx /
x.
0-
b0 ,
b0 +
b0 *
0)
b0 (
b0 '
b0 &
b0 %
0$
0#
0"
0!
$end
#5
19
#10
09
1G
#15
0.
bx 3
bx y
bx %
bx &"
bx 4
bx x
19
#20
b11110 v
0S
b10100 U
1Z
0_
0\
0Y
0a
0^
0]
0[
0b
0X
0`
1p
0d
0h
0g
0c
0j
0o
0i
0e
0f
0n
0k
0m
0l
0R
b10100 w
b1010 u
b10100 V
b1010 W
09
b11 :
b11 H
b10 <
b10 J
b1 ;
b1 I
1>
b1000000000000 T
b1000000000000 E
b1000000000000 Q
b0 C
b0 O
b10100 @
b10100 M
b1010 ?
b1010 L
b0 D
b0 P
b0 =
b0 K
b1000000000000 +"
b0 )"
b10100 -"
b1010 ,"
b0 *"
b0 ("
#25
1.
1"
1#
b11110 '"
b11110 /
b11110 }
b10100 *
b10100 ""
b1010 +
b1010 !"
b10 1
b10 {
b1 2
b1 z
bx (
bx #"
b11 3
b11 y
b1000000000000 %
b1000000000000 &"
b1000000000000 4
b1000000000000 x
19
#26
b11110 U
0p
1d
b10100 v
b11110 w
b110010 u
b11110 V
b110010 W
b1000000000100 T
b1000000000100 E
b1000000000100 Q
b11110 @
b11110 M
b110010 ?
b110010 L
b1 =
b1 K
b1000000000100 +"
b11110 -"
b110010 ,"
b1 ("
#30
09
#35
b11110 ,
b11110 ~
b10100 /
b10100 }
b11110 *
b11110 ""
b110010 +
b110010 !"
b1 0
b1 |
b10100 '"
bx (
bx #"
1.
1#
1"
b1000000000100 %
b1000000000100 &"
b1000000000100 4
b1000000000100 x
19
#36
b11 U
0d
1i
b1000 v
b11 w
b1 u
b11 V
b1 W
b1000000001000 T
b1000000001000 E
b1000000001000 Q
b11 @
b11 M
b1 ?
b1 L
b111 =
b111 K
b1000000001000 +"
b11 -"
b1 ,"
b111 ("
#40
09
#45
b1000 /
b1000 }
b11 *
b11 ""
b1 +
b1 !"
b1000 '"
bx (
bx #"
b111 0
b111 |
1.
1#
1"
b10100 ,
b10100 ~
b1000000001000 %
b1000000001000 &"
b1000000001000 4
b1000000001000 x
19
#46
b10 U
0i
1f
b11111111111111111111111111111100 v
b10 w
b11111111111111111111111111110000 u
b10 V
b11111111111111111111111111110000 W
b1000000001100 T
b1000000001100 E
b1000000001100 Q
b10 @
b10 M
b11111111111111111111111111110000 ?
b11111111111111111111111111110000 L
b1001 =
b1001 K
b1000000001100 +"
b10 -"
b11111111111111111111111111110000 ,"
b1001 ("
#50
09
#55
b11111111111111111111111111111100 /
b11111111111111111111111111111100 }
b10 *
b10 ""
b11111111111111111111111111110000 +
b11111111111111111111111111110000 !"
b11111111111111111111111111111100 '"
bx (
bx #"
b1001 0
b1001 |
1.
1#
1"
b1000 ,
b1000 ~
b1000000001100 %
b1000000001100 &"
b1000000001100 4
b1000000001100 x
19
#56
b10100 U
0Z
1[
1p
0f
b10101011110011010001001000110100 v
b10101011110011010001001000110100 w
b0 u
b0 V
b0 W
b1000000010000 T
b1000000010000 E
b1000000010000 Q
b10101011110011010001001000110100 C
b10101011110011010001001000110100 O
b0 @
b0 M
b0 ?
b0 L
b111 D
b111 P
b0 =
b0 K
b1000000010000 +"
b10101011110011010001001000110100 )"
b0 -"
b0 ,"
b111 *"
b0 ("
#60
09
#65
b10101011110011010001001000110100 /
b10101011110011010001001000110100 }
b10101011110011010001001000110100 '
b10101011110011010001001000110100 $"
b0 *
b0 ""
b0 +
b0 !"
b111 &
b111 %"
b10101011110011010001000000000000 '"
bx (
bx #"
b0 0
b0 |
1.
1#
1"
b11111111111111111111111111111100 ,
b11111111111111111111111111111100 ~
b1000000010000 %
b1000000010000 &"
b1000000010000 4
b1000000010000 x
19
