source/fetch_instruction.v
`ifndef FETCH_INSTRUCTION_V
`define FETCH_INSTRUCTION_V

module instruction_fetch #(
    parameter IWIDTH = 32,
    parameter AWIDTH_INSTR = 32,
    parameter PC_WIDTH = 32
)(
    f_clk, f_rst, f_i_instr, f_o_instr, f_o_addr_instr, f_change_pc, f_alu_pc_value, 
    f_pc, f_o_syn, f_i_ack, f_i_stall, f_o_ce, f_o_stall, f_i_flush, f_o_flush
);
    input f_clk, f_rst;
    //Instruction
    output reg [AWIDTH_INSTR - 1 : 0] f_o_addr_instr;
    input [IWIDTH - 1: 0] f_i_instr;
    output reg [IWIDTH - 1: 0] f_o_instr;
    output f_o_syn;
    input f_i_ack;
    //PC
    input f_change_pc;
    input [PC_WIDTH - 1 : 0] f_alu_pc_value;
    output reg [PC_WIDTH - 1: 0] f_pc;
    //Stall 
    input f_i_stall;
    output reg f_o_stall;
    output reg f_o_ce;
    input f_i_flush;
    output reg f_o_flush;

    reg [PC_WIDTH - 1 : 0] prev_pc;
    reg [AWIDTH_INSTR - 1 : 0] i_addr_instr;
    reg ce, ce_d;
    assign f_o_syn = ce;
    wire stall = f_o_stall || f_i_stall || (f_o_syn && !f_i_ack) || !f_o_syn;

    always @(posedge f_clk or negedge f_rst) begin
        if (!f_rst) begin
            f_o_stall <= 0;
            ce <= 0;
        end
        else if (f_i_flush) begin
            ce <= 1'b0;
            f_o_stall <= 1'b1;
        end
        else if ((f_change_pc || f_i_ack) && !(f_i_stall || f_o_stall)) begin
            ce <= 0;
            f_o_stall <= 1'b0;
        end
        else begin
            ce <= 1;
        end
    end

    always @(posedge f_clk or negedge f_rst) begin
        if (!f_rst) begin
            f_o_stall <= 0;
            f_o_flush <= 0;
            f_o_instr <= {IWIDTH{1'b0}};
            f_pc <= {PC_WIDTH{1'b0}};
            i_addr_instr <= {AWIDTH_INSTR{1'b0}};
            f_o_addr_instr <= {AWIDTH_INSTR{1'b0}};
            prev_pc <= {PC_WIDTH{1'b0}};
            ce_d <= 1'b0;
        end
        else begin
            if (f_i_flush) begin
                f_o_flush <= 1'b1;
                f_o_instr <= {IWIDTH{1'b0}};
            end
            if ((ce && f_i_ack && !stall) || (stall && !f_o_ce && ce)) begin
                i_addr_instr <= prev_pc; 
                f_o_addr_instr <= i_addr_instr;
                f_o_instr <= f_i_instr;
                f_o_flush <= 1'b0;
            end
            if (stall) begin
                f_o_ce <= 0;
            end
            else begin
                f_o_ce <= ce_d;
            end
            if (f_i_ack) begin
                prev_pc <= f_pc;
                if (f_change_pc || f_i_flush) begin
                    f_pc <= f_alu_pc_value; 
                end
                else begin
                    f_pc <= f_pc + 4;
                    ce_d <= ce;
                end
            end
        end
    end
endmodule
`endif

source/transmit_instruction.v
`ifndef TRANSMIT_INSTRUCTION_V
`define TRANSMIT_INSTRUCTION_V

module transmit #(
    parameter IWIDTH = 32,
    parameter DEPTH  = 36,
    parameter DWIDTH = 32
)(
    t_clk, t_rst, t_i_syn, t_o_instr, t_o_ack
);
    input  t_clk;
    input  t_rst;
    input  t_i_syn;
    output reg [IWIDTH - 1 : 0] t_o_instr;
    output reg t_o_ack;

    integer counter;
    reg [IWIDTH-1:0] mem_instr [0 : DEPTH - 1];

    always @(posedge t_clk or negedge t_rst) begin
        if (!t_rst) begin
            counter   <= {DWIDTH{1'b0}};
            t_o_ack   <= 1'b0;
            t_o_instr <= {IWIDTH{1'b0}};
            // nạp hex hoặc bin, kèm start-stop
            $readmemh("./source/instr.txt", mem_instr, 0, DEPTH - 1);
        end
        else begin
            if (t_i_syn) begin
                t_o_instr <= mem_instr[counter];
                t_o_ack   <= 1'b1;
                // if (counter < DEPTH - 1) begin
                //     counter <= counter + 1;
                // end
                // else begin
                //     counter <= 0;
                // end
                counter <= (counter < DEPTH - 1) ? counter + 1 : 0;
            end
            else begin
                t_o_ack <= 1'b0;
            end
        end
    end
endmodule
`endif

source/fetch_stage.v
`ifndef FETCH_STAGE_V
`define FETCH_STAGE_V
`include "./source/fetch_instruction.v"
`include "./source/transmit_instruction.v"

module fetch_i #(
    parameter IWIDTH = 32, 
    parameter DEPTH = 36,
    parameter AWIDTH_INSTR = 32,
    parameter PC_WIDTH = 32
)(
    fi_clk, fi_rst, fi_o_instr_fetch, fi_o_addr_instr, fi_change_pc, fi_alu_pc_value, 
    fi_pc, fi_i_stall, fi_o_stall, fi_o_ce, fi_i_flush, fi_o_flush
);
    input fi_clk, fi_rst;
    output [IWIDTH - 1 : 0] fi_o_instr_fetch;
    output [AWIDTH_INSTR - 1 : 0] fi_o_addr_instr;
    input fi_change_pc;
    input [PC_WIDTH - 1 : 0] fi_alu_pc_value;
    output [PC_WIDTH - 1 : 0] fi_pc;
    input fi_i_stall;
    output fi_o_stall;
    input fi_i_flush;
    output fi_o_flush;
    output fi_o_ce;
    wire [IWIDTH - 1 : 0] fi_o_instr_mem;

    wire fi_i_syn;
    wire fi_o_ack;

    transmit #(
        .IWIDTH(IWIDTH),
        .DEPTH(DEPTH)
    ) t (
        .t_clk(fi_clk),
        .t_rst(fi_rst),
        .t_i_syn(fi_i_syn),
        .t_o_instr(fi_o_instr_mem),
        .t_o_ack(fi_o_ack)
    );

    instruction_fetch #(
        .IWIDTH(IWIDTH),
        .AWIDTH_INSTR(AWIDTH_INSTR),
        .PC_WIDTH(PC_WIDTH)
    ) f (
        .f_clk(fi_clk),
        .f_rst(fi_rst),
        .f_i_instr(fi_o_instr_mem),
        .f_o_instr(fi_o_instr_fetch),
        .f_o_addr_instr(fi_o_addr_instr),
        .f_change_pc(fi_change_pc),
        .f_alu_pc_value(fi_alu_pc_value),
        .f_pc(fi_pc),
        .f_o_syn(fi_i_syn),
        .f_i_ack(fi_o_ack),
        .f_i_stall(fi_i_stall),
        .f_o_ce(fi_o_ce),
        .f_o_stall(fi_o_stall),
        .f_o_flush(fi_o_flush),
        .f_i_flush(fi_i_flush)
    );
endmodule
`endif

test/tb_fetch_stage.v
`include "./source/fetch_stage.v"
module tb;
    parameter IWIDTH = 32;
    parameter DEPTH = 36;
    parameter AWIDTH_INSTR = 32;
    parameter PC_WIDTH = 32;
    reg fi_clk, fi_rst;
    wire [IWIDTH - 1 : 0] fi_o_instr_fetch;
    wire [AWIDTH_INSTR - 1 : 0] fi_o_addr_instr;
    reg fi_change_pc;
    reg [PC_WIDTH - 1 : 0] fi_alu_pc_value;
    wire [PC_WIDTH - 1 : 0] fi_pc;
    reg fi_i_stall;
    wire fi_o_stall, fi_o_ce;
    reg fi_i_flush;
    wire fi_o_flush;
    integer i;

    fetch_i #(
        .IWIDTH(IWIDTH),
        .DEPTH(DEPTH),
        .AWIDTH_INSTR(AWIDTH_INSTR),
        .PC_WIDTH(PC_WIDTH)
    ) fi (
        .fi_clk(fi_clk), 
        .fi_rst(fi_rst), 
        .fi_o_instr_fetch(fi_o_instr_fetch), 
        .fi_o_addr_instr(fi_o_addr_instr), 
        .fi_change_pc(fi_change_pc), 
        .fi_alu_pc_value(fi_alu_pc_value), 
        .fi_pc(fi_pc), 
        .fi_i_stall(fi_i_stall), 
        .fi_o_stall(fi_o_stall), 
        .fi_o_ce(fi_o_ce),
        .fi_i_flush(fi_i_flush),
        .fi_o_flush(fi_o_flush)
    );

    initial begin
        fi_clk = 1'b0;
        fi_i_stall = 1'b0;
        fi_i_flush = 1'b0;
        i = 0;
    end
    always #5 fi_clk = ~fi_clk;

    initial begin
        $dumpfile("./waveform/fetch_stage.vcd");
        $dumpvars(0, tb);
    end

    task reset(input integer counter);
        begin 
            fi_rst = 1'b0;
            repeat(counter) @(posedge fi_clk);
            fi_rst = 1'b1;
        end
    endtask

    task display (input integer counter);
        begin
            for (i = 0; i < counter; i = i + 1) begin
                @(posedge fi_clk);
                $display($time, " ", "addr = %d, instruction = %h, syn = %b, ack = %b", i, fi_o_instr_fetch, fi.fi_i_syn, fi.fi_o_ack);
            end
        end
    endtask

    initial begin
        reset(2);
        @(posedge fi_clk);
        display(36);
        #200; $finish;
    end
endmodule

waveform/fetch_stage.vcd
$date
	Fri Aug 08 00:22:05 2025
$end
$version
	Icarus Verilog
$end
$timescale
	1s
$end
$scope module tb $end
$var wire 32 ! fi_pc [31:0] $end
$var wire 1 " fi_o_stall $end
$var wire 32 # fi_o_instr_fetch [31:0] $end
$var wire 1 $ fi_o_flush $end
$var wire 1 % fi_o_ce $end
$var wire 32 & fi_o_addr_instr [31:0] $end
$var parameter 32 ' AWIDTH_INSTR $end
$var parameter 32 ( DEPTH $end
$var parameter 32 ) IWIDTH $end
$var parameter 32 * PC_WIDTH $end
$var reg 32 + fi_alu_pc_value [31:0] $end
$var reg 1 , fi_change_pc $end
$var reg 1 - fi_clk $end
$var reg 1 . fi_i_flush $end
$var reg 1 / fi_i_stall $end
$var reg 1 0 fi_rst $end
$var integer 32 1 i [31:0] $end
$scope module fi $end
$var wire 32 2 fi_alu_pc_value [31:0] $end
$var wire 1 , fi_change_pc $end
$var wire 1 - fi_clk $end
$var wire 1 . fi_i_flush $end
$var wire 1 / fi_i_stall $end
$var wire 1 0 fi_rst $end
$var wire 32 3 fi_pc [31:0] $end
$var wire 1 " fi_o_stall $end
$var wire 32 4 fi_o_instr_mem [31:0] $end
$var wire 32 5 fi_o_instr_fetch [31:0] $end
$var wire 1 $ fi_o_flush $end
$var wire 1 % fi_o_ce $end
$var wire 32 6 fi_o_addr_instr [31:0] $end
$var wire 1 7 fi_o_ack $end
$var wire 1 8 fi_i_syn $end
$var parameter 32 9 AWIDTH_INSTR $end
$var parameter 32 : DEPTH $end
$var parameter 32 ; IWIDTH $end
$var parameter 32 < PC_WIDTH $end
$scope module f $end
$var wire 32 = f_alu_pc_value [31:0] $end
$var wire 1 , f_change_pc $end
$var wire 1 - f_clk $end
$var wire 1 . f_i_flush $end
$var wire 1 / f_i_stall $end
$var wire 1 8 f_o_syn $end
$var wire 1 0 f_rst $end
$var wire 1 > stall $end
$var wire 32 ? f_i_instr [31:0] $end
$var wire 1 7 f_i_ack $end
$var parameter 32 @ AWIDTH_INSTR $end
$var parameter 32 A IWIDTH $end
$var parameter 32 B PC_WIDTH $end
$var reg 1 8 ce $end
$var reg 1 C ce_d $end
$var reg 32 D f_o_addr_instr [31:0] $end
$var reg 1 % f_o_ce $end
$var reg 1 $ f_o_flush $end
$var reg 32 E f_o_instr [31:0] $end
$var reg 1 " f_o_stall $end
$var reg 32 F f_pc [31:0] $end
$var reg 32 G i_addr_instr [31:0] $end
$var reg 32 H prev_pc [31:0] $end
$upscope $end
$scope module t $end
$var wire 1 - t_clk $end
$var wire 1 8 t_i_syn $end
$var wire 1 0 t_rst $end
$var parameter 32 I DEPTH $end
$var parameter 32 J IWIDTH $end
$var reg 1 7 t_o_ack $end
$var reg 32 K t_o_instr [31:0] $end
$var integer 32 L counter [31:0] $end
$upscope $end
$upscope $end
$scope task display $end
$var integer 32 M counter [31:0] $end
$upscope $end
$scope task reset $end
$var integer 32 N counter [31:0] $end
$upscope $end
$upscope $end
$enddefinitions $end
$comment Show the parameter values. $end
$dumpall
b100000 J
b100100 I
b100000 B
b100000 A
b100000 @
b100000 <
b100000 ;
b100100 :
b100000 9
b100000 *
b100000 )
b100100 (
b100000 '
$end
#0
$dumpvars
b10 N
bx M
b0 L
b0 K
b0 H
b0 G
b0 F
b0 E
b0 D
0C
b0 ?
1>
bx =
08
07
b0 6
b0 5
b0 4
b0 3
bx 2
b0 1
00
0/
0.
0-
x,
bx +
b0 &
x%
0$
b0 #
0"
b0 !
$end
#5
1-
#10
0-
#15
1>
18
0%
10
1-
#20
0-
#25
0>
b1 L
17
b1100010000000010110011 4
b1100010000000010110011 ?
b1100010000000010110011 K
b100100 M
1-
#30
0-
#35
1>
b10 L
b1000000011000101000001000110011 4
b1000000011000101000001000110011 ?
b1000000011000101000001000110011 K
08
1C
b100 !
b100 3
b100 F
b1100010000000010110011 #
b1100010000000010110011 5
b1100010000000010110011 E
b1 1
1-
#40
0-
#45
0C
b1000 !
b1000 3
b1000 F
b100 H
07
b10 1
1-
#50
0-
#55
1>
18
b11 1
1-
#60
0-
#65
0>
b1000000011000101000001000110011 #
b1000000011000101000001000110011 5
b1000000011000101000001000110011 E
b100 G
b11 L
17
b100101000010001110110011 4
b100101000010001110110011 ?
b100101000010001110110011 K
b100 1
1-
#70
0-
#75
1>
b100 L
b110001011011010100110011 4
b110001011011010100110011 ?
b110001011011010100110011 K
08
1C
b1100 !
b1100 3
b1100 F
b1000 H
b100101000010001110110011 #
b100101000010001110110011 5
b100101000010001110110011 E
b100 &
b100 6
b100 D
b101 1
1-
#80
0-
#85
0C
b10000 !
b10000 3
b10000 F
b1100 H
07
b110 1
1-
#90
0-
#95
1>
18
b111 1
1-
#100
0-
#105
0>
b110001011011010100110011 #
b110001011011010100110011 5
b110001011011010100110011 E
b1100 G
b101 L
17
b111101110100011010110011 4
b111101110100011010110011 ?
b111101110100011010110011 K
b1000 1
1-
#110
0-
#115
1>
b110 L
b1001010001110100000110011 4
b1001010001110100000110011 ?
b1001010001110100000110011 K
08
1C
b10100 !
b10100 3
b10100 F
b10000 H
b111101110100011010110011 #
b111101110100011010110011 5
b111101110100011010110011 E
b1100 &
b1100 6
b1100 D
b1001 1
1-
#120
0-
#125
0C
b11000 !
b11000 3
b11000 F
b10100 H
07
b1010 1
1-
#130
0-
#135
1>
18
b1011 1
1-
#140
0-
#145
0>
b1001010001110100000110011 #
b1001010001110100000110011 5
b1001010001110100000110011 E
b10100 G
b111 L
17
b1010110100111100110110011 4
b1010110100111100110110011 ?
b1010110100111100110110011 K
b1100 1
1-
#150
0-
#155
1>
b1000 L
b1100010111001101100110011 4
b1100010111001101100110011 ?
b1100010111001101100110011 K
08
1C
b11100 !
b11100 3
b11100 F
b11000 H
b1010110100111100110110011 #
b1010110100111100110110011 5
b1010110100111100110110011 E
b10100 &
b10100 6
b10100 D
b1101 1
1-
#160
0-
#165
0C
b100000 !
b100000 3
b100000 F
b11100 H
07
b1110 1
1-
#170
0-
#175
1>
18
b1111 1
1-
#180
0-
#185
0>
b1100010111001101100110011 #
b1100010111001101100110011 5
b1100010111001101100110011 E
b11100 G
b1001 L
17
b1101101011101100110110011 4
b1101101011101100110110011 ?
b1101101011101100110110011 K
b10000 1
1-
#190
0-
#195
1>
b1010 L
b1000001111011101101111010110011 4
b1000001111011101101111010110011 ?
b1000001111011101101111010110011 K
08
1C
b100100 !
b100100 3
b100100 F
b100000 H
b1101101011101100110110011 #
b1101101011101100110110011 5
b1101101011101100110110011 E
b11100 &
b11100 6
b11100 D
b10001 1
1-
#200
0-
#205
0C
b101000 !
b101000 3
b101000 F
b100100 H
07
b10010 1
1-
#210
0-
#215
1>
18
b10011 1
1-
#220
0-
#225
0>
b1000001111011101101111010110011 #
b1000001111011101101111010110011 5
b1000001111011101101111010110011 E
b100100 G
b1011 L
17
b10100010000000010010011 4
b10100010000000010010011 ?
b10100010000000010010011 K
b10100 1
1-
#230
0-
#235
1>
b1100 L
b101000100010001010010011 4
b101000100010001010010011 ?
b101000100010001010010011 K
08
1C
b101100 !
b101100 3
b101100 F
b101000 H
b10100010000000010010011 #
b10100010000000010010011 5
b10100010000000010010011 E
b100100 &
b100100 6
b100100 D
b10101 1
1-
#240
0-
#245
0C
b110000 !
b110000 3
b110000 F
b101100 H
07
b10110 1
1-
#250
0-
#255
1>
18
b10111 1
1-
#260
0-
#265
0>
b101000100010001010010011 #
b101000100010001010010011 5
b101000100010001010010011 E
b101100 G
b1101 L
17
b100110011001100010011 4
b100110011001100010011 ?
b100110011001100010011 K
b11000 1
1-
#270
0-
#275
1>
b1110 L
b111101000100001110010011 4
b111101000100001110010011 ?
b111101000100001110010011 K
08
1C
b110100 !
b110100 3
b110100 F
b110000 H
b100110011001100010011 #
b100110011001100010011 5
b100110011001100010011 E
b101100 &
b101100 6
b101100 D
b11001 1
1-
#280
0-
#285
0C
b111000 !
b111000 3
b111000 F
b110100 H
07
b11010 1
1-
#290
0-
#295
1>
18
b11011 1
1-
#300
0-
#305
0>
b111101000100001110010011 #
b111101000100001110010011 5
b111101000100001110010011 E
b110100 G
b1111 L
17
b11111111111101010101011010010011 4
b11111111111101010101011010010011 ?
b11111111111101010101011010010011 K
b11100 1
1-
#310
0-
#315
1>
b10000 L
b11101100111011000010011 4
b11101100111011000010011 ?
b11101100111011000010011 K
08
1C
b111100 !
b111100 3
b111100 F
b111000 H
b11111111111101010101011010010011 #
b11111111111101010101011010010011 5
b11111111111101010101011010010011 E
b110100 &
b110100 6
b110100 D
b11101 1
1-
#320
0-
#325
0C
b1000000 !
b1000000 3
b1000000 F
b111100 H
07
b11110 1
1-
#330
0-
#335
1>
18
b11111 1
1-
#340
0-
#345
0>
b11101100111011000010011 #
b11101100111011000010011 5
b11101100111011000010011 E
b111100 G
b10001 L
17
b1011100101110110010011 4
b1011100101110110010011 ?
b1011100101110110010011 K
b100000 1
1-
#350
0-
#355
1>
b10010 L
b1100001111100010010011 4
b1100001111100010010011 ?
b1100001111100010010011 K
08
1C
b1000100 !
b1000100 3
b1000100 F
b1000000 H
b1011100101110110010011 #
b1011100101110110010011 5
b1011100101110110010011 E
b111100 &
b111100 6
b111100 D
b100001 1
1-
#360
0-
#365
0C
b1001000 !
b1001000 3
b1001000 F
b1000100 H
07
b100010 1
1-
#370
0-
#375
1>
18
b100011 1
1-
#380
0-
#385
0>
b1100001111100010010011 #
b1100001111100010010011 5
b1100001111100010010011 E
b1000100 G
b10011 L
17
b1000001000100101010000100010011 4
b1000001000100101010000100010011 ?
b1000001000100101010000100010011 K
b100100 1
1-
#390
0-
#395
1>
b10100 L
b1000000010000000000000011 4
b1000000010000000000000011 ?
b1000000010000000000000011 K
08
1C
b1001100 !
b1001100 3
b1001100 F
b1001000 H
b1000001000100101010000100010011 #
b1000001000100101010000100010011 5
b1000001000100101010000100010011 E
b1000100 &
b1000100 6
b1000100 D
1-
#400
0-
#405
0C
b1010000 !
b1010000 3
b1010000 F
b1001100 H
07
1-
#410
0-
#415
1>
18
1-
#420
0-
#425
0>
b1000000010000000000000011 #
b1000000010000000000000011 5
b1000000010000000000000011 E
b1001100 G
b10101 L
17
b10000000100010000100000011 4
b10000000100010000100000011 ?
b10000000100010000100000011 K
1-
#430
0-
#435
1>
b10110 L
b100000000101010000100000011 4
b100000000101010000100000011 ?
b100000000101010000100000011 K
08
1C
b1010100 !
b1010100 3
b1010100 F
b1010000 H
b10000000100010000100000011 #
b10000000100010000100000011 5
b10000000100010000100000011 E
b1001100 &
b1001100 6
b1001100 D
1-
#440
0-
#445
0C
b1011000 !
b1011000 3
b1011000 F
b1010100 H
07
1-
#450
0-
#455
1>
18
1-
#460
0-
#465
0>
b100000000101010000100000011 #
b100000000101010000100000011 5
b100000000101010000100000011 E
b1010100 G
b10111 L
17
b1000000000101011000110000011 4
b1000000000101011000110000011 ?
b1000000000101011000110000011 K
1-
#470
0-
#475
1>
b11000 L
b100101010010100000100011 4
b100101010010100000100011 ?
b100101010010100000100011 K
08
1C
b1011100 !
b1011100 3
b1011100 F
b1011000 H
b1000000000101011000110000011 #
b1000000000101011000110000011 5
b1000000000101011000110000011 E
b1010100 &
b1010100 6
b1010100 D
1-
#480
0-
#485
0C
b1100000 !
b1100000 3
b1100000 F
b1011100 H
07
1-
#490
0-
#495
1>
18
1-
#500
0-
#505
0>
b100101010010100000100011 #
b100101010010100000100011 5
b100101010010100000100011 E
b1011100 G
b11001 L
17
b101101100000110000100011 4
b101101100000110000100011 ?
b101101100000110000100011 K
1-
#510
0-
#515
1>
b11010 L
b1101011010110101000100011 4
b1101011010110101000100011 ?
b1101011010110101000100011 K
08
1C
b1100100 !
b1100100 3
b1100100 F
b1100000 H
b101101100000110000100011 #
b101101100000110000100011 5
b101101100000110000100011 E
b1011100 &
b1011100 6
b1011100 D
1-
#520
0-
#525
0C
b1101000 !
b1101000 3
b1101000 F
b1100100 H
07
1-
#530
0-
#535
1>
18
1-
#540
0-
#545
0>
b1101011010110101000100011 #
b1101011010110101000100011 5
b1101011010110101000100011 E
b1100100 G
b11011 L
17
b1000001000011001100011 4
b1000001000011001100011 ?
b1000001000011001100011 K
1-
#550
0-
#555
1>
b11100 L
b1000010000011001100011 4
b1000010000011001100011 ?
b1000010000011001100011 K
08
1C
b1101100 !
b1101100 3
b1101100 F
b1101000 H
b1000001000011001100011 #
b1000001000011001100011 5
b1000001000011001100011 E
b1100100 &
b1100100 6
b1100100 D
1-
#560
0-
#565
0C
b1110000 !
b1110000 3
b1110000 F
b1101100 H
07
1-
#570
0-
#575
1>
18
1-
#580
0-
#585
0>
b1000010000011001100011 #
b1000010000011001100011 5
b1000010000011001100011 E
b1101100 G
b11101 L
17
b1000110000011001100011 4
b1000110000011001100011 ?
b1000110000011001100011 K
1-
