source/fetch_instruction.v
`ifndef FETCH_INSTRUCTION_V
`define FETCH_INSTRUCTION_V

module instruction_fetch #(
    parameter IWIDTH = 32,
    parameter AWIDTH_INSTR = 32,
    parameter PC_WIDTH = 32
)(
    f_clk, f_rst, f_i_instr, f_o_instr, f_o_addr_instr, f_change_pc, f_alu_pc_value, 
    f_pc, f_o_syn, f_i_ack, f_i_stall, f_o_ce, f_o_stall, f_i_flush, f_o_flush, f_i_ce,
    f_i_last
);
    input f_clk, f_rst;
    //Instruction
    output reg [AWIDTH_INSTR - 1 : 0] f_o_addr_instr;
    input [IWIDTH - 1: 0] f_i_instr;
    output reg [IWIDTH - 1: 0] f_o_instr;
    output reg f_o_syn;
    input f_i_ack;
    input f_i_last;
    //PC
    input f_change_pc;
    input [PC_WIDTH - 1 : 0] f_alu_pc_value;
    output reg [PC_WIDTH - 1: 0] f_pc;
    //Stall 
    input f_i_stall;
    output reg f_o_stall;
    input f_i_ce;
    output reg f_o_ce;
    input f_i_flush;
    output reg f_o_flush;
    //Internal state regs
    reg ce, ce_d;
    reg f_o_syn_r;
    wire stall = f_o_stall || f_i_stall || (f_o_syn_r && !f_i_ack);
    reg init_done;
    reg temp_ack, temp_last;
    reg req; //Req is value equal to syn is used as a replacement variable in some conditions coordinate the pc and syn signal
    reg [PC_WIDTH - 1 : 0] issued_pc; //This variable is used for the temporary storage of the PC value each time it is updated

    //The solution of using temporary variables and replacement variables with the same meaning is avoid falling into race signals leading to a deadlock
    always @(posedge f_clk, negedge f_rst) begin
        if (!f_rst) begin
            f_o_stall <= 1'b0;
            ce <= 1'b0;
            ce_d <= 1'b0;
            f_o_ce <= 1'b0;
            f_o_flush <= 1'b0;
            f_o_stall <= 1'b0;
            f_o_instr <= {IWIDTH{1'b0}};
            f_pc <= {PC_WIDTH{1'b0}};
            f_o_addr_instr <= {AWIDTH_INSTR{1'b0}};
            f_o_syn_r <= 1'b0;
            f_o_syn <= 1'b0;
            init_done <= 1'b0;
            temp_ack <= 1'b0;
            temp_last <= 1'b0;
            req <= 1'b0;
            issued_pc <= {PC_WIDTH{1'b0}};
        end
        else begin
            if (!init_done) begin
                init_done <= 1'b1;
                //Fix syn chạy trước i_ce được bật 
                if (f_i_ce) begin
                    req <= 1'b1;
                    f_o_syn <= 1'b1;
                    f_o_syn_r <= 1'b1;
                    f_pc <= f_pc + 4;
                    issued_pc <= f_pc;
                end
                else begin
                    req <= 1'b0;
                    f_o_syn <= 1'b0;
                    f_o_syn_r <= 1'b0;
                end
            end
            else begin
                // flush handling: stop requests
                if (f_i_flush) begin
                    req <= 1'b0;
                    f_o_syn <= 1'b0;
                    f_o_stall <= 1'b1;
                    f_o_flush <= 1'b1;
                end
                else begin
                    // if external CE, allow re-issue if no outstanding req and not stalled
                    if (!req && (ce || f_i_ce) && !f_i_stall && !f_o_stall) begin
                        req <= 1'b1;
                        f_o_syn <= 1'b1;
                        f_pc <= f_pc + 4;
                        issued_pc <= f_pc;
                    end
                    // change PC: handle on ack event below 
                    if ((f_change_pc || f_i_ack) && !(f_i_stall || f_o_stall)) begin
                        ce <= 1'b1;
                        f_o_stall <= 1'b0;
                        f_o_flush <= 1'b0;
                    end
                end

                if (stall) begin
                    f_o_ce <= 1'b0;
                end
                else begin
                    f_o_ce <= ce_d;
                end

                if (f_i_stall) begin
                    f_o_stall <= 1'b1; 
                end
                else if (!f_i_flush) begin
                    f_o_stall <= 1'b0;
                end
                f_o_syn_r <= f_o_syn;
            end
        end
    end
    //Combinative of always is used to 
    always @(*) begin
        temp_ack = f_i_ack;
        temp_last = f_i_last;
        // When ack = 1, consume returned instruction
        if (temp_ack) begin
            f_o_addr_instr = issued_pc;
            f_o_instr = f_i_instr;
            f_o_flush = 1'b0;
            // if slave said last, stop request; otherwise continue streaming
            if (temp_last) begin
                req = 1'b0;
                f_o_syn = 1'b0;
            end
            else begin
                req = 1'b1;
                f_o_syn = 1'b1;
                f_pc = f_pc + 4;
                issued_pc = f_pc;
            end
            // handle change PC / flush on ack
            if (f_change_pc || f_i_flush) begin
                f_pc = f_alu_pc_value;
            end
            else begin
                ce_d = ce; 
            end
        end
    end
endmodule
`endif

test/tb_fetch_instruction.v
`timescale 1ns/1ps
`include "./source/fetch_instruction.v"

module tb_instruction_fetch;
    // Parameters
    parameter IWIDTH        = 32;
    parameter AWIDTH_INSTR  = 32;
    parameter PC_WIDTH      = 32;
    parameter DEPTH         = 32; // local memory entries for TB

    // Clock and reset
    reg                    f_clk;
    reg                    f_rst;

    // DUT interface
    reg  [IWIDTH-1:0]      f_i_instr;        // data from "transmit" (emulated here)
    wire [IWIDTH-1:0]      f_o_instr;        // output of fetch (to decoder)
    wire [AWIDTH_INSTR-1:0] f_o_addr_instr;
    wire                   f_o_syn;          // request from fetch (to mem/transmit)
    reg                    f_i_ack;          // ack from mem/transmit (emulated)
    reg                    f_i_last;
    reg                    f_i_stall;        // downstream stall input (consumer busy)
    wire                   f_o_stall;        // fetch asserts when it cannot accept more requests
    reg                    f_i_ce;           // allow fetch
    wire                   f_o_ce;           // valid output to downstream
    reg                    f_i_flush;
    wire                   f_o_flush;
    reg                    f_change_pc;
    reg  [PC_WIDTH-1:0]    f_alu_pc_value;
    wire [PC_WIDTH-1:0]    f_pc;
    integer i;
    // Instantiate DUT
    instruction_fetch #(
        .IWIDTH(IWIDTH),
        .AWIDTH_INSTR(AWIDTH_INSTR),
        .PC_WIDTH(PC_WIDTH)
    ) dut (
        .f_clk         (f_clk),
        .f_rst         (f_rst),
        .f_i_instr     (f_i_instr),
        .f_o_instr     (f_o_instr),
        .f_o_addr_instr(f_o_addr_instr),
        .f_change_pc   (f_change_pc),
        .f_alu_pc_value(f_alu_pc_value),
        .f_pc          (f_pc),
        .f_o_syn       (f_o_syn),
        .f_i_ack       (f_i_ack),
        .f_i_stall     (f_i_stall),
        .f_o_stall     (f_o_stall),
        .f_i_ce        (f_i_ce),
        .f_o_ce        (f_o_ce),
        .f_i_flush     (f_i_flush),
        .f_o_flush     (f_o_flush),
        .f_i_last      (f_i_last)
    );

    // Simple memory to emulate transmit: feed deterministic words
    reg [IWIDTH-1:0] mem [0:DEPTH-1];
    integer mem_ptr;

    // Clock
    initial begin
        f_clk = 0;
        i = 0;
        forever #5 f_clk = ~f_clk; // 10 ns period
    end

    // Waveform
    initial begin
        $dumpfile("./waveform/fetch_instruction.vcd");
        $dumpvars(0, tb_instruction_fetch);
    end

    // Reset task
    task do_reset(input integer cycles);
        begin
            f_rst = 0;
            repeat(cycles) @(posedge f_clk);
            f_rst = 1;
            @(posedge f_clk);
        end
    endtask

    // Stall task (downstream busy)
    task introduce_stall(input integer cycles);
        begin
            f_i_stall = 1;
            repeat(cycles) @(posedge f_clk);
            f_i_stall = 0;
            @(posedge f_clk);
        end
    endtask

    // Jump task: request PC change for one cycle
    task do_jump(input [PC_WIDTH-1:0] pc);
        begin
            f_alu_pc_value = pc;
            f_change_pc    = 1;
            @(posedge f_clk);
            f_change_pc = 0;
            @(posedge f_clk);
        end
    endtask

    // Flush task: assert flush for given cycles
    task do_flush(input integer cycles);
        integer i;
        begin
            f_i_flush = 1;
            @(posedge f_clk);
            for (i = 1; i < cycles; i = i + 1)
                @(posedge f_clk);
            f_i_flush = 0;
            @(posedge f_clk);
        end
    endtask

    // Emulate transmit/memory behavior:
    // - When f_o_syn==1, present f_i_instr = mem[mem_ptr] and assert f_i_ack = 1 for that cycle.
    // - Advance mem_ptr each time f_o_syn is asserted.
    always @(posedge f_clk or negedge f_rst) begin
        if (!f_rst) begin
            f_i_instr <= {IWIDTH{1'b0}};
            f_i_ack   <= 1'b0;
            f_i_last  <= 1'b0;
            mem_ptr   <= 0;
            for (i = 0; i <= DEPTH; i = i + 1) begin
                mem[i] = 32'h1000_0000 + i; // simple increasing patterns for visibility
            end
        end 
        else begin
            if (f_o_syn) begin
                f_i_instr <= mem[mem_ptr];
                f_i_ack   <= 1'b1;
                // advance pointer so next request gets next instruction
                mem_ptr <= (mem_ptr < DEPTH - 1) ? mem_ptr + 1 : 0;
                f_i_last <= (mem_ptr == DEPTH - 1) ? 1 : 0;
            end 
            else begin
                f_i_ack <= 1'b0;
                f_i_last <= 1'b0;
            end
        end
    end

    // Monitoring: print concise table each cycle
    initial begin
        
        forever @(posedge f_clk) begin
            $display($time, " ", "clk = %b, rst = %b, pc = %h, addr_req = %h, instr_in = %h, syn = %b, ack = %b, stall_i = %b, stall_o = %b, ce = %b, out_flush = %b, f_i_last = %b", 
                     f_clk, f_rst,
                     f_pc, f_o_addr_instr, f_i_instr,
                     f_o_syn, f_i_ack, f_i_stall, f_o_stall, f_o_ce, f_o_flush, f_i_last);
        end
    end

    // Test sequence
    initial begin
        // defaults
        f_i_instr       = 0;
        f_i_ack         = 0;
        f_i_stall       = 0;
        f_change_pc     = 0;
        f_alu_pc_value  = 0;
        f_i_flush       = 0;
        f_i_ce          = 0; // allow fetch to start
        // reset
        do_reset(2);
        f_i_ce          = 1; // allow fetch to start

        // let DUT run and fetch a few instructions automatically
        repeat (6) @(posedge f_clk); // observe startup

        // introduce stall for 4 cycles (downstream busy)
        $display(">>> Introduce stall (4 cycles)");
        introduce_stall(4);

        // wait a few cycles
        repeat (4) @(posedge f_clk);

        // jump to 0x100
        $display(">>> Jump to 0x100");
        do_jump(32'h00000100);

        // let fetch run a few cycles
        repeat (6) @(posedge f_clk);

        // flush pipeline for 2 cycles
        $display(">>> Flush for 2 cycles");
        do_flush(2);

        // allow more cycles to observe streaming
        repeat (7) @(posedge f_clk);
        $display("TEST COMPLETE");
        $finish;
    end

endmodule

waveform/fetch_instruction.vcd
$date
	Sat Aug 30 01:26:16 2025
$end
$version
	Icarus Verilog
$end
$timescale
	1ps
$end
$scope module tb_instruction_fetch $end
$var wire 32 ! f_pc [31:0] $end
$var wire 1 " f_o_syn $end
$var wire 1 # f_o_stall $end
$var wire 32 $ f_o_instr [31:0] $end
$var wire 1 % f_o_flush $end
$var wire 1 & f_o_ce $end
$var wire 32 ' f_o_addr_instr [31:0] $end
$var parameter 32 ( AWIDTH_INSTR $end
$var parameter 32 ) DEPTH $end
$var parameter 32 * IWIDTH $end
$var parameter 32 + PC_WIDTH $end
$var reg 32 , f_alu_pc_value [31:0] $end
$var reg 1 - f_change_pc $end
$var reg 1 . f_clk $end
$var reg 1 / f_i_ack $end
$var reg 1 0 f_i_ce $end
$var reg 1 1 f_i_flush $end
$var reg 32 2 f_i_instr [31:0] $end
$var reg 1 3 f_i_last $end
$var reg 1 4 f_i_stall $end
$var reg 1 5 f_rst $end
$var integer 32 6 i [31:0] $end
$var integer 32 7 mem_ptr [31:0] $end
$scope module dut $end
$var wire 32 8 f_alu_pc_value [31:0] $end
$var wire 1 - f_change_pc $end
$var wire 1 . f_clk $end
$var wire 1 / f_i_ack $end
$var wire 1 0 f_i_ce $end
$var wire 1 1 f_i_flush $end
$var wire 32 9 f_i_instr [31:0] $end
$var wire 1 3 f_i_last $end
$var wire 1 4 f_i_stall $end
$var wire 1 5 f_rst $end
$var wire 1 : stall $end
$var parameter 32 ; AWIDTH_INSTR $end
$var parameter 32 < IWIDTH $end
$var parameter 32 = PC_WIDTH $end
$var reg 1 > ce $end
$var reg 1 ? ce_d $end
$var reg 32 @ f_o_addr_instr [31:0] $end
$var reg 1 & f_o_ce $end
$var reg 1 % f_o_flush $end
$var reg 32 A f_o_instr [31:0] $end
$var reg 1 # f_o_stall $end
$var reg 1 " f_o_syn $end
$var reg 1 B f_o_syn_r $end
$var reg 32 C f_pc [31:0] $end
$var reg 1 D init_done $end
$var reg 32 E issued_pc [31:0] $end
$var reg 1 F req $end
$var reg 1 G temp_ack $end
$var reg 1 H temp_last $end
$upscope $end
$scope task do_flush $end
$var integer 32 I cycles [31:0] $end
$var integer 32 J i [31:0] $end
$upscope $end
$scope task do_jump $end
$var reg 32 K pc [31:0] $end
$upscope $end
$scope task do_reset $end
$var integer 32 L cycles [31:0] $end
$upscope $end
$scope task introduce_stall $end
$var integer 32 M cycles [31:0] $end
$upscope $end
$upscope $end
$enddefinitions $end
$comment Show the parameter values. $end
$dumpall
b100000 =
b100000 <
b100000 ;
b100000 +
b100000 *
b100000 )
b100000 (
$end
#0
$dumpvars
bx M
b10 L
bx K
bx J
bx I
0H
0G
0F
b0 E
0D
b0 C
0B
b0 A
b0 @
0?
0>
0:
b0 9
b0 8
b0 7
b100001 6
05
04
03
b0 2
01
00
0/
0.
0-
b0 ,
b0 '
0&
0%
b0 $
0#
0"
b0 !
$end
#5000
b100001 6
1.
#10000
0.
#15000
1D
15
1.
#20000
0.
#25000
b100 !
b100 C
1"
1F
10
1.
#30000
0.
#35000
b1000 E
b1000 !
b1000 C
b10000000000000000000000000000 $
b10000000000000000000000000000 A
1G
1B
b1 7
1/
b10000000000000000000000000000 2
b10000000000000000000000000000 9
1.
#40000
0.
#45000
1?
b1100 E
b1100 !
b1100 C
b10000000000000000000000000001 $
b10000000000000000000000000001 A
b1000 '
b1000 @
b10 7
b10000000000000000000000000001 2
b10000000000000000000000000001 9
1>
1.
#50000
0.
#55000
b10000 E
b10000 !
b10000 C
b10000000000000000000000000010 $
b10000000000000000000000000010 A
b1100 '
b1100 @
1&
b11 7
b10000000000000000000000000010 2
b10000000000000000000000000010 9
1.
#60000
0.
#65000
b10100 E
b10100 !
b10100 C
b10000000000000000000000000011 $
b10000000000000000000000000011 A
b10000 '
b10000 @
b100 7
b10000000000000000000000000011 2
b10000000000000000000000000011 9
1.
#70000
0.
#75000
b11000 E
b11000 !
b11000 C
b10000000000000000000000000100 $
b10000000000000000000000000100 A
b10100 '
b10100 @
b101 7
b10000000000000000000000000100 2
b10000000000000000000000000100 9
1.
#80000
0.
#85000
b11100 E
b11100 !
b11100 C
b10000000000000000000000000101 $
b10000000000000000000000000101 A
b11000 '
b11000 @
b110 7
b10000000000000000000000000101 2
b10000000000000000000000000101 9
1#
1:
14
b100 M
1.
#90000
0.
#95000
b100000 E
b100000 !
b100000 C
b10000000000000000000000000110 $
b10000000000000000000000000110 A
b11100 '
b11100 @
0&
b111 7
b10000000000000000000000000110 2
b10000000000000000000000000110 9
1.
#100000
0.
#105000
b100100 E
b100100 !
b100100 C
b10000000000000000000000000111 $
b10000000000000000000000000111 A
b100000 '
b100000 @
b1000 7
b10000000000000000000000000111 2
b10000000000000000000000000111 9
1.
#110000
0.
#115000
b101000 E
b101000 !
b101000 C
b10000000000000000000000001000 $
b10000000000000000000000001000 A
b100100 '
b100100 @
b1001 7
b10000000000000000000000001000 2
b10000000000000000000000001000 9
1.
#120000
0.
#125000
0:
b101100 E
b101100 !
b101100 C
b10000000000000000000000001001 $
b10000000000000000000000001001 A
b101000 '
b101000 @
b1010 7
b10000000000000000000000001001 2
b10000000000000000000000001001 9
0#
04
1.
#130000
0.
#135000
b110000 E
b110000 !
b110000 C
b10000000000000000000000001010 $
b10000000000000000000000001010 A
b101100 '
b101100 @
1&
b1011 7
b10000000000000000000000001010 2
b10000000000000000000000001010 9
1.
#140000
0.
#145000
b110100 E
b110100 !
b110100 C
b10000000000000000000000001011 $
b10000000000000000000000001011 A
b110000 '
b110000 @
b1100 7
b10000000000000000000000001011 2
b10000000000000000000000001011 9
1.
#150000
0.
#155000
b111000 E
b111000 !
b111000 C
b10000000000000000000000001100 $
b10000000000000000000000001100 A
b110100 '
b110100 @
b1101 7
b10000000000000000000000001100 2
b10000000000000000000000001100 9
1.
#160000
0.
#165000
b111100 E
b111100 !
b111100 C
b10000000000000000000000001101 $
b10000000000000000000000001101 A
b111000 '
b111000 @
b1110 7
b10000000000000000000000001101 2
b10000000000000000000000001101 9
1.
#170000
0.
#175000
b10000000000000000000000001110 $
b10000000000000000000000001110 A
b1111 7
b10000000000000000000000001110 2
b10000000000000000000000001110 9
b100000100 E
b100000000 !
b100000000 C
b1000000 '
b1000000 @
1-
b100000000 ,
b100000000 8
b100000000 K
1.
#180000
0.
#185000
b100001000 E
b10000000000000000000000001111 $
b10000000000000000000000001111 A
b10000 7
b10000000000000000000000001111 2
b10000000000000000000000001111 9
b100001000 !
b100001000 C
b100000100 '
b100000100 @
0-
1.
#190000
0.
#195000
b100001100 E
b100001100 !
b100001100 C
b10000000000000000000000010000 $
b10000000000000000000000010000 A
b100001000 '
b100001000 @
b10001 7
b10000000000000000000000010000 2
b10000000000000000000000010000 9
1.
#200000
0.
#205000
b100010000 E
b100010000 !
b100010000 C
b10000000000000000000000010001 $
b10000000000000000000000010001 A
b100001100 '
b100001100 @
b10010 7
b10000000000000000000000010001 2
b10000000000000000000000010001 9
1.
#210000
0.
#215000
b100010100 E
b100010100 !
b100010100 C
b10000000000000000000000010010 $
b10000000000000000000000010010 A
b100010000 '
b100010000 @
b10011 7
b10000000000000000000000010010 2
b10000000000000000000000010010 9
1.
#220000
0.
#225000
b100011000 E
b100011000 !
b100011000 C
b10000000000000000000000010011 $
b10000000000000000000000010011 A
b100010100 '
b100010100 @
b10100 7
b10000000000000000000000010011 2
b10000000000000000000000010011 9
1.
#230000
0.
#235000
b100011100 E
b100011100 !
b100011100 C
b10000000000000000000000010100 $
b10000000000000000000000010100 A
b100011000 '
b100011000 @
b10101 7
b10000000000000000000000010100 2
b10000000000000000000000010100 9
1.
#240000
0.
#245000
b100100000 E
b100100000 !
b100100000 C
b10000000000000000000000010101 $
b10000000000000000000000010101 A
b100011100 '
b100011100 @
b10110 7
b10000000000000000000000010101 2
b10000000000000000000000010101 9
1.
#250000
0.
#255000
1:
b10000000000000000000000010110 $
b10000000000000000000000010110 A
0%
1#
1"
1F
b10111 7
b10000000000000000000000010110 2
b10000000000000000000000010110 9
b100000100 E
b100000000 !
b100000000 C
b100100100 '
b100100100 @
11
b10 I
1.
#260000
0.
#265000
b100000000 !
b100000000 C
b10000000000000000000000010111 $
b10000000000000000000000010111 A
b100000100 '
b100000100 @
b11000 7
b10000000000000000000000010111 2
b10000000000000000000000010111 9
0&
0%
1"
1F
b1 J
1.
#270000
0.
#275000
0:
b100001000 E
b10000000000000000000000011000 $
b10000000000000000000000011000 A
0#
b11001 7
b10000000000000000000000011000 2
b10000000000000000000000011000 9
b100001000 !
b100001000 C
01
b10 J
1.
#280000
0.
#285000
b100001100 E
b100001100 !
b100001100 C
b10000000000000000000000011001 $
b10000000000000000000000011001 A
b100001000 '
b100001000 @
b11010 7
b10000000000000000000000011001 2
b10000000000000000000000011001 9
1&
1.
#290000
0.
#295000
b100010000 E
b100010000 !
b100010000 C
b10000000000000000000000011010 $
b10000000000000000000000011010 A
b100001100 '
b100001100 @
b11011 7
b10000000000000000000000011010 2
b10000000000000000000000011010 9
1.
#300000
0.
#305000
b100010100 E
b100010100 !
b100010100 C
b10000000000000000000000011011 $
b10000000000000000000000011011 A
b100010000 '
b100010000 @
b11100 7
b10000000000000000000000011011 2
b10000000000000000000000011011 9
1.
#310000
0.
#315000
b100011000 E
b100011000 !
b100011000 C
b10000000000000000000000011100 $
b10000000000000000000000011100 A
b100010100 '
b100010100 @
b11101 7
b10000000000000000000000011100 2
b10000000000000000000000011100 9
1.
#320000
0.
#325000
b100011100 E
b100011100 !
b100011100 C
b10000000000000000000000011101 $
b10000000000000000000000011101 A
b100011000 '
b100011000 @
b11110 7
b10000000000000000000000011101 2
b10000000000000000000000011101 9
1.
#330000
0.
#335000
b100100000 E
b100100000 !
b100100000 C
b10000000000000000000000011110 $
b10000000000000000000000011110 A
b100011100 '
b100011100 @
b11111 7
b10000000000000000000000011110 2
b10000000000000000000000011110 9
1.
#340000
0.
#345000
0"
0F
b10000000000000000000000011111 $
b10000000000000000000000011111 A
b100100000 '
b100100000 @
1H
13
b0 7
b10000000000000000000000011111 2
b10000000000000000000000011111 9
1.
#350000
0.
#355000
0H
0G
0B
b100100100 !
b100100100 C
1"
1F
03
0/
1.
