fetch.v
`ifndef FETCH_V
`define FETCH_V

module instruction_fetch #(
    parameter I_WIDTH = 32,
    parameter A_WIDTH = 32,
    parameter PC_WIDTH = 32
)(
    f_clk, f_rst_n, i_instr, o_instr, o_addr_instr, change_pc, alu_pc_value, pc, o_syn, i_ack, i_stall, o_ce
);
    input f_clk, f_rst_n;
    //Instruction
    output reg [A_WIDTH - 1 : 0] o_addr_instr;
    input [I_WIDTH - 1: 0] i_instr;
    output reg [I_WIDTH - 1: 0] o_instr;
    output o_syn;
    input i_ack;
    //PC
    input change_pc;
    input [PC_WIDTH - 1 : 0] alu_pc_value;
    output reg [PC_WIDTH - 1: 0] pc;
    //Stall 
    input i_stall;
    output reg o_ce;

    reg [PC_WIDTH - 1 : 0] prev_pc;
    reg [A_WIDTH - 1 : 0] i_addr_instr;
    reg ce, ce_d;
    reg stall_fetch;
    assign o_syn = ce;
    wire stall = stall_fetch || i_stall || (o_syn && !i_ack) || !o_syn;

    always @(posedge f_clk or negedge f_rst_n) begin
        if (!f_rst_n) begin
            ce <= 0;
        end
        else if ((change_pc || i_ack) && !(i_stall || stall_fetch)) begin
            ce <= 0;
        end
        else begin
            ce <= 1;
        end
    end

    always @(posedge f_clk or negedge f_rst_n) begin
        if (!f_rst_n) begin
            o_instr <= {I_WIDTH{1'b0}};
            pc <= {PC_WIDTH{1'b0}};
            i_addr_instr <= {A_WIDTH{1'b0}};
            o_addr_instr <= {A_WIDTH{1'b0}};
            prev_pc <= {PC_WIDTH{1'b0}};
            ce_d <= 1'b0;
        end
        else begin
            if ((ce && i_ack && !stall) || (stall && !o_ce && ce)) begin
                i_addr_instr <= prev_pc; 
                o_addr_instr <= i_addr_instr;
                o_instr <= i_instr;
            end
            if (stall) begin
                o_ce <= 0;
            end
            else begin
                o_ce <= ce_d;
            end
            if (i_ack) begin
                prev_pc <= pc;
                if (change_pc) begin
                    pc <= alu_pc_value; 
                end
                else begin
                    pc <= pc + 4;
                    ce_d <= ce;
                end
            end
        end
    end
endmodule
`endif

tb_fetch.v
`timescale 1ns/1ps
`include "fetch.v"
module tb_instruction_fetch;
    // Parameters
    parameter I_WIDTH   = 32;
    parameter A_WIDTH   = 32;
    parameter PC_WIDTH  = 32;

    // Clock and reset
    reg                    f_clk;
    reg                    f_rst_n;

    // Instruction interface
    reg  [I_WIDTH-1:0]     i_instr;
    wire [I_WIDTH-1:0]     o_instr;
    wire [A_WIDTH-1:0]     o_addr_instr;
    wire                   o_syn;
    reg                    i_ack;

    // Program counter interface
    reg                    change_pc;
    reg  [PC_WIDTH-1:0]    alu_pc_value;
    wire [PC_WIDTH-1:0]    pc;

    // Stall interface
    reg                    i_stall;
    wire                   o_ce;

    // Instantiate the DUT
    instruction_fetch #(
        .I_WIDTH(I_WIDTH),
        .A_WIDTH(A_WIDTH),
        .PC_WIDTH(PC_WIDTH)
    ) dut (
        .f_clk(f_clk),
        .f_rst_n(f_rst_n),
        .i_instr(i_instr),
        .o_instr(o_instr),
        .o_addr_instr(o_addr_instr),
        .change_pc(change_pc),
        .alu_pc_value(alu_pc_value),
        .pc(pc),
        .o_syn(o_syn),
        .i_ack(i_ack),
        .i_stall(i_stall),
        .o_ce(o_ce)
    );

    // Clock generation: 10 ns period
    initial f_clk = 1'b0;
    always #5 f_clk = ~f_clk;

    // Reset task
    task do_reset;
        input integer cycles;
        begin
            f_rst_n = 0;
            repeat (cycles) @(posedge f_clk);
            f_rst_n = 1;
            @(posedge f_clk);
        end
    endtask

    // Task to drive one instruction fetch
    task send_instruction (input [I_WIDTH - 1 : 0] instr);
        begin
            i_instr = instr;
            i_ack = 1'b1;
            i_stall = 1'b0;
            change_pc = 1'b0;
            @(posedge f_clk);
            i_ack = 1'b0;
            @(posedge f_clk);
        end
    endtask

    // Task to introduce a stall
    task introduce_stall (input integer counter_stall);
        begin
            i_stall = 1'b1;
            repeat (counter_stall) @(posedge f_clk);
            i_stall = 1'b0;
            @(posedge f_clk);
        end
    endtask

    // Task to change PC via jump
    task do_jump (input [PC_WIDTH - 1 : 0] pc_jump);
        begin
            alu_pc_value = pc_jump;
            change_pc = 1'b1;
            i_ack = 1'b1;
            @(posedge f_clk);
            change_pc = 1'b0;
            i_ack = 1'b0;
            @(posedge f_clk);
        end
    endtask

    // Monitoring signals
    initial begin
        $display("Time |   rst  | addr_req | instr_in  | ack | stall | syn | ce_out | pc_out | fetched_instr");
        $monitor("%4t |   %b    | %h  | %h |  %b  |   %b   |  %b  |   %b    | %h | %h", 
                 $time, f_rst_n, o_addr_instr, i_instr, i_ack, i_stall, o_syn, o_ce, pc, o_instr);
    end

    // Test sequence
    initial begin
        // Initialize inputs
        i_instr        = 32'h00000000;
        i_ack          = 0;
        i_stall        = 0;
        change_pc      = 0;
        alu_pc_value   = 32'h00000000;

        // Apply reset
        do_reset(2);

        // Normal fetch sequence: fetch 3 instructions
        send_instruction(32'hA0A0A0A0);
        send_instruction(32'hB1B1B1B1);
        send_instruction(32'hC2C2C2C2);

        // Introduce a stall for 3 cycles
        introduce_stall(3);

        // Continue fetching after stall
        send_instruction(32'hD3D3D3D3);

        // Change PC (jump) to address 0x100
        do_jump(32'h00000100);

        // Fetch 2 more instructions after jump
        send_instruction(32'hE4E4E4E4);
        send_instruction(32'hF5F5F5F5);

        // Finish simulation
        #20;
        $display("Test completed.");
        $finish;
    end
endmodule

waveform/fetch.vcd
$date
	Mon Jul 21 23:05:51 2025
$end
$version
	Icarus Verilog
$end
$timescale
	1ps
$end
$scope module tb_instruction_fetch $end
$var wire 32 ! pc [31:0] $end
$var wire 1 " o_syn $end
$var wire 32 # o_instr [31:0] $end
$var wire 1 $ o_ce $end
$var wire 32 % o_addr_instr [31:0] $end
$var parameter 32 & A_WIDTH $end
$var parameter 32 ' I_WIDTH $end
$var parameter 32 ( PC_WIDTH $end
$var reg 32 ) alu_pc_value [31:0] $end
$var reg 1 * change_pc $end
$var reg 1 + f_clk $end
$var reg 1 , f_rst_n $end
$var reg 1 - i_ack $end
$var reg 32 . i_instr [31:0] $end
$var reg 1 / i_stall $end
$scope module dut $end
$var wire 32 0 alu_pc_value [31:0] $end
$var wire 1 * change_pc $end
$var wire 1 + f_clk $end
$var wire 1 , f_rst_n $end
$var wire 1 - i_ack $end
$var wire 32 1 i_instr [31:0] $end
$var wire 1 / i_stall $end
$var wire 1 " o_syn $end
$var wire 1 2 stall $end
$var parameter 32 3 A_WIDTH $end
$var parameter 32 4 I_WIDTH $end
$var parameter 32 5 PC_WIDTH $end
$var reg 1 " ce $end
$var reg 1 6 ce_d $end
$var reg 32 7 i_addr_instr [31:0] $end
$var reg 32 8 o_addr_instr [31:0] $end
$var reg 1 $ o_ce $end
$var reg 32 9 o_instr [31:0] $end
$var reg 32 : pc [31:0] $end
$var reg 32 ; prev_pc [31:0] $end
$var reg 1 < stall_fetch $end
$upscope $end
$scope task do_jump $end
$var reg 32 = pc_jump [31:0] $end
$upscope $end
$scope task do_reset $end
$var integer 32 > cycles [31:0] $end
$upscope $end
$scope task introduce_stall $end
$var integer 32 ? counter_stall [31:0] $end
$upscope $end
$scope task send_instruction $end
$var reg 32 @ instr [31:0] $end
$upscope $end
$upscope $end
$enddefinitions $end
$comment Show the parameter values. $end
$dumpall
b100000 5
b100000 4
b100000 3
b100000 (
b100000 '
b100000 &
$end
#0
$dumpvars
bx @
bx ?
b10 >
bx =
x<
b0 ;
b0 :
b0 9
b0 8
b0 7
06
12
b0 1
b0 0
0/
b0 .
0-
0,
0+
0*
b0 )
b0 %
x$
b0 #
0"
b0 !
$end
#5000
1+
#10000
0+
#15000
12
1"
0$
1,
1+
#20000
0+
#25000
16
b100 !
b100 :
b10100000101000001010000010100000 #
b10100000101000001010000010100000 9
x2
1-
b10100000101000001010000010100000 .
b10100000101000001010000010100000 1
b10100000101000001010000010100000 @
1+
#30000
0+
#35000
1$
12
0-
1+
#40000
0+
#45000
b1000 !
b1000 :
b100 ;
0$
x2
1-
b10110001101100011011000110110001 .
b10110001101100011011000110110001 1
b10110001101100011011000110110001 @
1+
#50000
0+
#55000
1$
12
0-
1+
#60000
0+
#65000
b1100 !
b1100 :
b1000 ;
0$
x2
1-
b11000010110000101100001011000010 .
b11000010110000101100001011000010 1
b11000010110000101100001011000010 @
1+
#70000
0+
#75000
1$
12
0-
1+
#80000
0+
#85000
0$
1/
b11 ?
1+
#90000
0+
#95000
b11000010110000101100001011000010 #
b11000010110000101100001011000010 9
b1000 7
1+
#100000
0+
#105000
b1000 %
b1000 8
1+
#110000
0+
#115000
0/
1+
#120000
0+
#125000
b10000 !
b10000 :
b1100 ;
b11010011110100111101001111010011 #
b11010011110100111101001111010011 9
x2
1-
b11010011110100111101001111010011 .
b11010011110100111101001111010011 1
b11010011110100111101001111010011 @
1+
#130000
0+
#135000
1$
12
0-
1+
#140000
0+
#145000
b100000000 !
b100000000 :
b10000 ;
0$
x2
1-
1*
b100000000 )
b100000000 0
b100000000 =
1+
#150000
0+
#155000
1$
12
0-
0*
1+
#160000
0+
#165000
b100000100 !
b100000100 :
b100000000 ;
0$
x2
1-
b11100100111001001110010011100100 .
b11100100111001001110010011100100 1
b11100100111001001110010011100100 @
1+
#170000
0+
#175000
1$
12
0-
1+
#180000
0+
#185000
b100001000 !
b100001000 :
b100000100 ;
0$
x2
1-
b11110101111101011111010111110101 .
b11110101111101011111010111110101 1
b11110101111101011111010111110101 @
1+
#190000
0+
#195000
1$
12
0-
1+
#200000
0+
#205000
0$
1+
#210000
0+
#215000
b11110101111101011111010111110101 #
b11110101111101011111010111110101 9
b100000100 7
1+
#220000
0+
#225000
b100000100 %
b100000100 8
1+
