test_resource/memory.v
`ifndef MEMORY_V
`define MEMORY_V
module memory #(
    parameter AWIDTH = 5,
    parameter DWIDTH = 32,
    parameter DEPTH = 1 << AWIDTH
)(
    m_clk, m_rst, m_i_cyc, m_i_stb, m_i_we, m_i_rd, m_i_load_addr, m_i_store_addr, 
    m_i_data_store, m_o_read_data, m_o_ack, m_i_byte_enable, m_o_stall
);
    input m_clk, m_rst;
    input m_i_cyc;
    input m_i_stb;
    input m_i_we;
    input m_i_rd;
    input [3 : 0] m_i_byte_enable;
    input [AWIDTH - 1 : 0] m_i_load_addr;
    input [AWIDTH - 1 : 0] m_i_store_addr;
    input [DWIDTH - 1 : 0] m_i_data_store;
    output reg [DWIDTH - 1 : 0] m_o_read_data;
    output reg m_o_ack;
    output reg m_o_stall;

    reg req_active; // Variable transient for stall 
    reg [AWIDTH - 1 : 0] load_addr_reg;
    reg [AWIDTH - 1 : 0] store_addr_reg; 
    reg [DWIDTH - 1 : 0] data_reg;
    reg [DWIDTH - 1 : 0] mask_reg;
    reg we_reg, rd_reg;

    reg [DWIDTH - 1 : 0] data [DEPTH - 1 : 0];
    
    wire [DWIDTH - 1 : 0] mask = {
        {8{m_i_byte_enable[3]}},
        {8{m_i_byte_enable[2]}},
        {8{m_i_byte_enable[1]}},
        {8{m_i_byte_enable[0]}}
    };

    always @(posedge m_clk, negedge m_rst) begin
	 integer i;
        if (!m_rst) begin
            m_o_ack <= 1'b0;
            m_o_stall <= 1'b0;
            req_active <= 1'b0;
            m_o_read_data <= {DWIDTH{1'b0}};
            for (i = 0; i < DEPTH; i = i + 1) begin
                data[i] <= {DWIDTH{1'b0}};
            end
        end
        else begin
            m_o_ack <= 0;
            m_o_stall <= req_active;
// When there are storage requests, the full set of values will be prepared, such as the store
// value, store address when the value needs to be stored in memory, or the load address when 
// the value needs to be read from memory 
// All of signals below are used to receive adequate signals before being applied to memory, in order to avoid stalling
            if (!req_active) begin 
                if (m_i_cyc && m_i_stb) begin
                    load_addr_reg <= m_i_load_addr;
                    store_addr_reg <= m_i_store_addr;
                    data_reg <= m_i_data_store;
                    mask_reg <= mask;
                    we_reg <= m_i_we;
                    rd_reg <= m_i_rd;
                    req_active <= 1'b1;
                end
            end
// After preparation, the values will be retrieved from memory based on the read request or write 
// request signal, then pipeline will be delayed to done retrieval
            else begin
                if (we_reg) begin
                    data[store_addr_reg] <= (data[store_addr_reg] & ~mask_reg) | (data_reg & mask_reg);
                end
                if (rd_reg) begin
                    m_o_read_data <= data[load_addr_reg];
                end
                m_o_ack <= 1'b1;
                req_active <= 1'b0;
            end
        end
    end
endmodule
`endif

test/tb_memory.v
`timescale 1ns/1ps
`include "./source/memory.v"

module tb_memory;
    parameter AWIDTH = 5;
    parameter DWIDTH = 32;

    // Clock and Reset
    reg m_clk, m_rst;

    // Stimulus signals
    reg                   m_i_cyc;
    reg                   m_i_stb;
    reg                   m_i_we;
    reg                   m_i_rd;
    reg [3:0]             m_i_byte_enable;
    reg [AWIDTH-1:0]      m_i_load_addr;
    reg [AWIDTH-1:0]      m_i_store_addr;
    reg [DWIDTH-1:0]      m_i_data_store;

    // Outputs
    wire [DWIDTH-1:0]     m_o_read_data;
    wire                  m_o_ack;

    // Instantiate memory
    memory #(
        .AWIDTH(AWIDTH),
        .DWIDTH(DWIDTH)
    ) uut (
        .m_clk         (m_clk),
        .m_rst         (m_rst),
        .m_i_cyc       (m_i_cyc),
        .m_i_stb       (m_i_stb),
        .m_i_we        (m_i_we),
        .m_i_byte_enable (m_i_byte_enable),
        .m_i_load_addr (m_i_load_addr),
        .m_i_store_addr(m_i_store_addr),
        .m_i_data_store (m_i_data_store),
        .m_o_read_data (m_o_read_data),
        .m_o_ack       (m_o_ack),
        .m_i_rd(m_i_rd)
    );

    // Clock generator: 10 ns period
    initial begin
        m_clk = 0;
        forever #5 m_clk = ~m_clk;
    end

    // Reset task
    task reset();
        begin
            m_rst         = 0;
            m_i_cyc       = 0;
            m_i_stb       = 0;
            m_i_we        = 0;
            m_i_rd        = 0;
            m_i_byte_enable = 4'b0;
            m_i_load_addr = 0;
            m_i_store_addr= 0;
            m_i_data_store      = 0;
            #20;
            m_rst = 1;
        end
    endtask

    initial begin
        // Initialize and reset
        reset();
        @(posedge m_clk);

        // Write transaction: write 0xDEADBEEF to address 5
        m_i_cyc        = 1;
        m_i_stb        = 1;
        m_i_we         = 1;
        m_i_byte_enable  = 4'b1111;        // full word byte-enable
        m_i_store_addr = 5;
        m_i_data_store       = 32'hDEADBEEF;
        @(posedge m_clk);
        // wait for ack
        wait (m_o_ack);
        $display("%0t WRITE ACK, addr=%0d data=0x%h", $time, m_i_store_addr, m_i_data_store);
        // deassert
        m_i_cyc = 0;
        m_i_stb = 0;
        m_i_we  = 0;
        @(posedge m_clk);

        // Read transaction: read from address 5
        m_i_cyc       = 1;
        m_i_stb       = 1;
        m_i_rd        = 1;
        m_i_load_addr = 5;
        @(posedge m_clk);
        wait (m_o_ack);
        $display("%0t READ  ACK, addr=%0d data=0x%h", $time, m_i_load_addr, m_o_read_data);
        // deassert
        m_i_cyc = 0;
        m_i_stb = 0;
        @(posedge m_clk);

        #20;
        $finish;
    end
endmodule

waveform/memory.vcd
$date
	Mon Sep 08 01:45:57 2025
$end
$version
	Icarus Verilog
$end
$timescale
	1ps
$end
$scope module tb_memory $end
$var wire 32 ! m_o_read_data [31:0] $end
$var wire 1 " m_o_ack $end
$var parameter 32 # AWIDTH $end
$var parameter 32 $ DWIDTH $end
$var reg 1 % m_clk $end
$var reg 4 & m_i_byte_enable [3:0] $end
$var reg 1 ' m_i_cyc $end
$var reg 32 ( m_i_data_store [31:0] $end
$var reg 5 ) m_i_load_addr [4:0] $end
$var reg 1 * m_i_rd $end
$var reg 1 + m_i_stb $end
$var reg 5 , m_i_store_addr [4:0] $end
$var reg 1 - m_i_we $end
$var reg 1 . m_rst $end
$scope module uut $end
$var wire 1 % m_clk $end
$var wire 4 / m_i_byte_enable [3:0] $end
$var wire 1 ' m_i_cyc $end
$var wire 32 0 m_i_data_store [31:0] $end
$var wire 5 1 m_i_load_addr [4:0] $end
$var wire 1 * m_i_rd $end
$var wire 1 + m_i_stb $end
$var wire 5 2 m_i_store_addr [4:0] $end
$var wire 1 - m_i_we $end
$var wire 1 . m_rst $end
$var wire 32 3 mask [31:0] $end
$var parameter 32 4 AWIDTH $end
$var parameter 37 5 DEPTH $end
$var parameter 32 6 DWIDTH $end
$var reg 32 7 data_reg [31:0] $end
$var reg 5 8 load_addr_reg [4:0] $end
$var reg 1 " m_o_ack $end
$var reg 32 9 m_o_read_data [31:0] $end
$var reg 1 : m_o_stall $end
$var reg 32 ; mask_reg [31:0] $end
$var reg 1 < rd_reg $end
$var reg 1 = req_active $end
$var reg 5 > store_addr_reg [4:0] $end
$var reg 1 ? we_reg $end
$var integer 32 @ i [31:0] $end
$upscope $end
$scope task reset $end
$upscope $end
$upscope $end
$enddefinitions $end
$comment Show the parameter values. $end
$dumpall
b100000 6
b100000 5
b101 4
b100000 $
b101 #
$end
#0
$dumpvars
b100000 @
x?
bx >
0=
x<
bx ;
0:
b0 9
bx 8
bx 7
b0 3
b0 2
b0 1
b0 0
b0 /
0.
0-
b0 ,
0+
0*
b0 )
b0 (
0'
b0 &
0%
0"
b0 !
$end
#5000
b100000 @
1%
#10000
0%
#15000
b100000 @
1%
#20000
0%
1.
#25000
1=
0<
1?
b0 ;
b11011110101011011011111011101111 7
b101 >
b0 8
b11111111111111111111111111111111 3
b11011110101011011011111011101111 (
b11011110101011011011111011101111 0
b101 ,
b101 2
b1111 &
b1111 /
1-
1+
1'
1%
#30000
0%
#35000
0-
0+
0'
0=
1"
1:
1%
#40000
0%
#45000
1=
1<
0?
b11111111111111111111111111111111 ;
b101 8
0:
0"
b101 )
b101 1
1*
1+
1'
1%
#50000
0%
#55000
0+
0'
0=
1"
b11011110101011011011111011101111 !
b11011110101011011011111011101111 9
1:
1%
#60000
0%
#65000
0:
0"
1%
