source/register_file.v
`ifndef REGISTER_FILE
`define REGISTER_FILE

module register #(
    parameter DWIDTH = 32,
    parameter AWIDTH = 32
)(
    r_clk, r_rst, r_addr, r_data_in, r_data_out, r_we
);
    input r_clk, r_rst;
    input r_we;
    input [AWIDTH - 1 : 0] r_addr;
    input [DWIDTH - 1 : 0] r_data_in;
    output reg [DWIDTH - 1 : 0] r_data_out;

    integer i;
    reg [DWIDTH - 1 : 0] data [AWIDTH - 1 : 0];

    always @(posedge r_clk, negedge r_rst) begin
        if (!r_rst) begin
            for (i = 0; i < AWIDTH; i = i + 1) begin
                data[i] <= {DWIDTH{1'b0}};
            end
            r_data_out <= {DWIDTH{1'b0}};
        end
        else begin
            if (r_we) begin
                data[r_addr] <= r_data_in;
            end
            r_data_out <= data[r_addr];
        end
    end
endmodule
`endif

testbench/tb_register_file.v
`include "./source/register_file.v"

module tb;
    parameter AWIDTH = 32, DWIDTH = 32;
    reg r_clk, r_rst;
    reg r_we;
    reg [AWIDTH - 1 : 0] r_addr;
    reg [DWIDTH - 1 : 0] r_data_in;
    wire [DWIDTH - 1 : 0] r_data_out;
    integer i;
    register #(
        .AWIDTH(AWIDTH),
        .DWIDTH(DWIDTH)
    ) r (
        .r_clk(r_clk),
        .r_rst(r_rst),
        .r_we(r_we),
        .r_addr(r_addr),
        .r_data_in(r_data_in),
        .r_data_out(r_data_out)
    );

    initial begin
        r_clk = 1'b0;
        i = 0;
        r_we = 1'b0;
    end 
    always #5 r_clk = ~r_clk;

    initial begin
        $dumpfile("./waveform/register_file.vcd");
        $dumpvars(0, tb);
    end

    task reset (input integer counter);
        begin
            r_rst = 1'b0;
            repeat(counter) @(posedge r_clk);
            r_rst = 1'b1;
        end
    endtask

    task load (input integer counter);
        begin
            for (i = 0; i < counter; i = i + 1) begin
                r_we = 1'b1;
                @(posedge r_clk);
                r_addr = i;
                r_data_in = i;
                @(posedge r_clk);
                r_we = 1'b0;
            end
        end
    endtask

    task display (input integer counter);
        begin
            for (i = 0; i < counter; i = i + 1) begin
                @(posedge r_clk);
                r_addr = i;
                @(posedge r_clk);
                $display($time, " ", "addr = %d, data = %d", r_addr, r_data_out);
                @(posedge r_clk);
            end
        end
    endtask

    initial begin
        reset(2);
        load(10);
        display(10);
        #200; $finish;
    end
endmodule

waveform/register_file.vcd
$date
	Thu Jul 24 15:05:07 2025
$end
$version
	Icarus Verilog
$end
$timescale
	1s
$end
$scope module tb $end
$var wire 32 ! r_data_out [31:0] $end
$var parameter 32 " AWIDTH $end
$var parameter 32 # DWIDTH $end
$var reg 32 $ r_addr [31:0] $end
$var reg 1 % r_clk $end
$var reg 32 & r_data_in [31:0] $end
$var reg 1 ' r_rst $end
$var reg 1 ( r_we $end
$var integer 32 ) i [31:0] $end
$scope module r $end
$var wire 32 * r_addr [31:0] $end
$var wire 1 % r_clk $end
$var wire 32 + r_data_in [31:0] $end
$var wire 1 ' r_rst $end
$var wire 1 ( r_we $end
$var parameter 32 , AWIDTH $end
$var parameter 32 - DWIDTH $end
$var reg 32 . r_data_out [31:0] $end
$var integer 32 / i [31:0] $end
$upscope $end
$scope task display $end
$var integer 32 0 counter [31:0] $end
$upscope $end
$scope task load $end
$var integer 32 1 counter [31:0] $end
$upscope $end
$scope task reset $end
$var integer 32 2 counter [31:0] $end
$upscope $end
$upscope $end
$enddefinitions $end
$comment Show the parameter values. $end
$dumpall
b100000 -
b100000 ,
b100000 #
b100000 "
$end
#0
$dumpvars
b10 2
bx 1
bx 0
b100000 /
b0 .
bx +
bx *
b0 )
0(
0'
bx &
0%
bx $
b0 !
$end
#5
b100000 /
1%
#10
0%
#15
bx !
bx .
1(
b1010 1
1'
1%
#20
0%
#25
b0 !
b0 .
b0 &
b0 +
b0 $
b0 *
1%
#30
0%
#35
b1 )
1(
1%
#40
0%
#45
b1 &
b1 +
b1 $
b1 *
1%
#50
0%
#55
b1 !
b1 .
b10 )
1(
1%
#60
0%
#65
b0 !
b0 .
b10 &
b10 +
b10 $
b10 *
1%
#70
0%
#75
b10 !
b10 .
b11 )
1(
1%
#80
0%
#85
b0 !
b0 .
b11 &
b11 +
b11 $
b11 *
1%
#90
0%
#95
b11 !
b11 .
b100 )
1(
1%
#100
0%
#105
b0 !
b0 .
b100 &
b100 +
b100 $
b100 *
1%
#110
0%
#115
b100 !
b100 .
b101 )
1(
1%
#120
0%
#125
b0 !
b0 .
b101 &
b101 +
b101 $
b101 *
1%
#130
0%
#135
b101 !
b101 .
b110 )
1(
1%
#140
0%
#145
b0 !
b0 .
b110 &
b110 +
b110 $
b110 *
1%
#150
0%
#155
b110 !
b110 .
b111 )
1(
1%
#160
0%
#165
b0 !
b0 .
b111 &
b111 +
b111 $
b111 *
1%
#170
0%
#175
b111 !
b111 .
b1000 )
1(
1%
#180
0%
#185
b0 !
b0 .
b1000 &
b1000 +
b1000 $
b1000 *
1%
#190
0%
#195
b1000 !
b1000 .
b1001 )
1(
1%
#200
0%
#205
b0 !
b0 .
b1001 &
b1001 +
b1001 $
b1001 *
1%
#210
0%
#215
b1001 !
b1001 .
b1010 0
b0 )
0(
1%
#220
0%
#225
b0 !
b0 .
b0 $
b0 *
1%
#230
0%
#235
1%
#240
0%
#245
b1 )
1%
#250
0%
#255
b1 !
b1 .
b1 $
b1 *
1%
#260
0%
#265
1%
#270
0%
#275
b10 )
1%
#280
0%
#285
b10 !
b10 .
b10 $
b10 *
1%
#290
0%
#295
1%
#300
0%
#305
b11 )
1%
#310
0%
#315
b11 !
b11 .
b11 $
b11 *
1%
#320
0%
#325
1%
#330
0%
#335
b100 )
1%
#340
0%
#345
b100 !
b100 .
b100 $
b100 *
1%
#350
0%
#355
1%
#360
0%
#365
b101 )
1%
#370
0%
#375
b101 !
b101 .
b101 $
b101 *
1%
#380
0%
#385
1%
#390
0%
#395
b110 )
1%
#400
0%
#405
b110 !
b110 .
b110 $
b110 *
1%
#410
0%
#415
1%
#420
0%
#425
b111 )
1%
#430
0%
#435
b111 !
b111 .
b111 $
b111 *
1%
#440
0%
#445
1%
#450
0%
#455
b1000 )
1%
#460
0%
#465
b1000 !
b1000 .
b1000 $
b1000 *
1%
#470
0%
#475
1%
#480
0%
#485
b1001 )
1%
#490
0%
#495
b1001 !
b1001 .
b1001 $
b1001 *
1%
#500
0%
#505
1%
#510
0%
#515
b1010 )
1%
