source/transmit_instruction.v
`ifndef TRANSMIT_INSTRUCTION_V
`define TRANSMIT_INSTRUCTION_V

module transmit #(
    parameter IWIDTH = 32,
    parameter DEPTH  = 36,
    parameter DWIDTH = 32
)(
    t_clk, t_rst, t_i_syn, t_o_instr, t_o_ack
);
    input  t_clk;
    input  t_rst;
    input  t_i_syn;
    output reg [IWIDTH - 1 : 0] t_o_instr;
    output reg t_o_ack;

    integer counter;
    reg [IWIDTH-1:0] mem_instr [0 : DEPTH - 1];

    always @(posedge t_clk or negedge t_rst) begin
        if (!t_rst) begin
            counter   <= {DWIDTH{1'b0}};
            t_o_ack   <= 1'b0;
            t_o_instr <= {IWIDTH{1'b0}};
            // nạp hex hoặc bin, kèm start-stop
            $readmemh("./source/instr.txt", mem_instr, 0, DEPTH - 1);
        end
        else begin
            if (t_i_syn) begin
                t_o_instr <= mem_instr[counter];
                t_o_ack   <= 1'b1;
                // if (counter < DEPTH - 1) begin
                //     counter <= counter + 1;
                // end
                // else begin
                //     counter <= 0;
                // end
                counter <= (counter < DEPTH - 1) ? counter + 1 : 0;
            end
            else begin
                t_o_ack <= 1'b0;
            end
        end
    end
endmodule
`endif

test/tb_transmit_instruction.v
`include "./instruction/transmit_instruction.v"

module tb;
    parameter IWIDTH = 32;
    reg t_clk, t_rst;
    wire [IWIDTH - 1 : 0] t_o_instr;
    reg t_i_syn;
    wire t_o_ack;
    integer i;

    transmit #(
        .IWIDTH(IWIDTH)
    ) t (
        .t_clk(t_clk),
        .t_rst(t_rst),
        .t_o_instr(t_o_instr),
        .t_i_syn(t_i_syn),
        .t_o_ack(t_o_ack)
    );

    initial begin
        t_clk = 0;
        t_i_syn = 0;
        i = 0;
    end
    always #5 t_clk = ~t_clk;

    task reset (input integer counter);
        begin
            t_rst = 1'b0;
            repeat(counter) @(posedge t_clk);
            t_rst = 1'b1;
        end
    endtask

    task display (input integer counter);
        begin
            for (i = 0; i < counter; i = i + 1) begin
                @(posedge t_clk);
                t_i_syn = 1'b1;
                @(posedge t_clk);
                $display($time, " ", "instr = %h, ack = %b", t_o_instr, t_o_ack);
                @(posedge t_clk);
                t_i_syn = 1'b0;
                @(posedge t_clk);
            end
        end
    endtask

    initial begin
        reset(2);
        @(posedge t_clk);
        display(30);
        #200; $finish;
    end
endmodule

waveform/transmit.vcd
$date
	Sat Aug 09 12:00:28 2025
$end
$version
	Icarus Verilog
$end
$timescale
	1s
$end
$scope module tb $end
$var wire 32 ! t_o_instr [31:0] $end
$var wire 1 " t_o_ack $end
$var parameter 32 # IWIDTH $end
$var reg 1 $ t_clk $end
$var reg 1 % t_i_syn $end
$var reg 1 & t_rst $end
$var integer 32 ' i [31:0] $end
$scope module t $end
$var wire 1 $ t_clk $end
$var wire 1 % t_i_syn $end
$var wire 1 & t_rst $end
$var parameter 32 ( DEPTH $end
$var parameter 32 ) IWIDTH $end
$var reg 1 " t_o_ack $end
$var reg 32 * t_o_instr [31:0] $end
$var integer 32 + counter [31:0] $end
$upscope $end
$scope task display $end
$var integer 32 , counter [31:0] $end
$upscope $end
$scope task reset $end
$var integer 32 - counter [31:0] $end
$upscope $end
$upscope $end
$enddefinitions $end
$comment Show the parameter values. $end
$dumpall
b100000 )
b100100 (
b100000 #
$end
#0
$dumpvars
b10 -
bx ,
b0 +
b0 *
b0 '
0&
0%
0$
0"
b0 !
$end
#5
1$
#10
0$
#15
1&
1$
#20
0$
#25
b11110 ,
1$
#30
0$
#35
b1 +
1"
b1100010000000010110011 !
b1100010000000010110011 *
1%
1$
#40
0$
#45
b10 +
b1000000011000101000001000110011 !
b1000000011000101000001000110011 *
1$
#50
0$
#55
0"
0%
1$
#60
0$
#65
b1 '
1$
#70
0$
#75
b11 +
1"
b100101000010001110110011 !
b100101000010001110110011 *
1%
1$
#80
0$
#85
b100 +
b110001011011010100110011 !
b110001011011010100110011 *
1$
#90
0$
#95
0"
0%
1$
#100
0$
#105
b10 '
1$
#110
0$
#115
b101 +
1"
b111101110100011010110011 !
b111101110100011010110011 *
1%
1$
#120
0$
#125
b110 +
b1001010001110100000110011 !
b1001010001110100000110011 *
1$
#130
0$
#135
0"
0%
1$
#140
0$
#145
b11 '
1$
#150
0$
#155
b111 +
1"
b1010110100111100110110011 !
b1010110100111100110110011 *
1%
1$
#160
0$
#165
b1000 +
b1100010111001101100110011 !
b1100010111001101100110011 *
1$
#170
0$
#175
0"
0%
1$
#180
0$
#185
b100 '
1$
#190
0$
#195
b1001 +
1"
b1101101011101100110110011 !
b1101101011101100110110011 *
1%
1$
#200
0$
#205
b1010 +
b1000001111011101101111010110011 !
b1000001111011101101111010110011 *
1$
#210
0$
#215
0"
0%
1$
#220
0$
#225
b101 '
1$
#230
0$
#235
b1011 +
1"
b10100010000000010010011 !
b10100010000000010010011 *
1%
1$
#240
0$
#245
b1100 +
b101000100010001010010011 !
b101000100010001010010011 *
1$
#250
0$
#255
0"
0%
1$
#260
0$
#265
b110 '
1$
#270
0$
#275
b1101 +
1"
b100110011001100010011 !
b100110011001100010011 *
1%
1$
#280
0$
#285
b1110 +
b111101000100001110010011 !
b111101000100001110010011 *
1$
#290
0$
#295
0"
0%
1$
#300
0$
#305
b111 '
1$
#310
0$
#315
b1111 +
1"
b11111111111101010101011010010011 !
b11111111111101010101011010010011 *
1%
1$
#320
0$
#325
b10000 +
b11101100111011000010011 !
b11101100111011000010011 *
1$
#330
0$
#335
0"
0%
1$
#340
0$
#345
b1000 '
1$
#350
0$
#355
b10001 +
1"
b1011100101110110010011 !
b1011100101110110010011 *
1%
1$
#360
0$
#365
b10010 +
b1100001111100010010011 !
b1100001111100010010011 *
1$
#370
0$
#375
0"
0%
1$
#380
0$
#385
b1001 '
1$
#390
0$
#395
b10011 +
1"
b1000001000100101010000100010011 !
b1000001000100101010000100010011 *
1%
1$
#400
0$
#405
b10100 +
b1000000010000000000000011 !
b1000000010000000000000011 *
1$
#410
0$
#415
0"
0%
1$
#420
0$
#425
b1010 '
1$
#430
0$
#435
b10101 +
1"
b10000000100010000100000011 !
b10000000100010000100000011 *
1%
1$
#440
0$
#445
b10110 +
b100000000101010000100000011 !
b100000000101010000100000011 *
1$
#450
0$
#455
0"
0%
1$
#460
0$
#465
b1011 '
1$
#470
0$
#475
b10111 +
1"
b1000000000101011000110000011 !
b1000000000101011000110000011 *
1%
1$
#480
0$
#485
b11000 +
b100101010010100000100011 !
b100101010010100000100011 *
1$
#490
0$
#495
0"
0%
1$
#500
0$
#505
b1100 '
1$
#510
0$
#515
b11001 +
1"
b101101100000110000100011 !
b101101100000110000100011 *
1%
1$
#520
0$
#525
b11010 +
b1101011010110101000100011 !
b1101011010110101000100011 *
1$
#530
0$
#535
0"
0%
1$
#540
0$
#545
b1101 '
1$
#550
0$
#555
b11011 +
1"
b1000001000011001100011 !
b1000001000011001100011 *
1%
1$
#560
0$
#565
b11100 +
b1000010000011001100011 !
b1000010000011001100011 *
1$
#570
0$
#575
0"
0%
1$
#580
0$
#585
b1110 '
1$
#590
0$
#595
b11101 +
1"
b1000110000011001100011 !
b1000110000011001100011 *
1%
1$
#600
0$
#605
b11110 +
b1000111000011001100011 !
b1000111000011001100011 *
1$
#610
0$
#615
0"
0%
1$
#620
0$
#625
b1111 '
1$
#630
0$
#635
b11111 +
1"
b1001000000011001100011 !
b1001000000011001100011 *
1%
1$
#640
0$
#645
b100000 +
b1001001000011001100011 !
b1001001000011001100011 *
1$
#650
0$
#655
0"
0%
1$
#660
0$
#665
b10000 '
1$
#670
0$
#675
b100001 +
1"
b1000000000000001000000011101111 !
b1000000000000001000000011101111 *
1%
1$
#680
0$
#685
b100010 +
b1000000011000000101100111 !
b1000000011000000101100111 *
1$
#690
0$
#695
0"
0%
1$
#700
0$
#705
b10001 '
1$
#710
0$
#715
b100011 +
1"
b10010001101000101001010110111 !
b10010001101000101001010110111 *
1%
1$
#720
0$
#725
b0 +
b10000000000000000001100010111 !
b10000000000000000001100010111 *
1$
#730
0$
#735
0"
0%
1$
#740
0$
#745
b10010 '
1$
#750
0$
#755
b1 +
1"
b1100010000000010110011 !
b1100010000000010110011 *
1%
1$
#760
0$
#765
b10 +
b1000000011000101000001000110011 !
b1000000011000101000001000110011 *
1$
#770
0$
#775
0"
0%
1$
#780
0$
#785
b10011 '
1$
#790
0$
#795
b11 +
1"
b100101000010001110110011 !
b100101000010001110110011 *
1%
1$
#800
0$
#805
b100 +
b110001011011010100110011 !
b110001011011010100110011 *
1$
#810
0$
#815
0"
0%
1$
#820
0$
#825
b10100 '
1$
#830
0$
#835
b101 +
1"
b111101110100011010110011 !
b111101110100011010110011 *
1%
1$
#840
0$
#845
b110 +
b1001010001110100000110011 !
b1001010001110100000110011 *
1$
#850
0$
#855
0"
0%
1$
#860
0$
#865
b10101 '
1$
#870
0$
#875
b111 +
1"
b1010110100111100110110011 !
b1010110100111100110110011 *
1%
1$
#880
0$
#885
b1000 +
b1100010111001101100110011 !
b1100010111001101100110011 *
1$
#890
0$
#895
0"
0%
1$
#900
0$
#905
b10110 '
1$
#910
0$
#915
b1001 +
1"
b1101101011101100110110011 !
b1101101011101100110110011 *
1%
1$
#920
0$
#925
b1010 +
b1000001111011101101111010110011 !
b1000001111011101101111010110011 *
1$
#930
0$
#935
0"
0%
1$
#940
0$
#945
b10111 '
1$
#950
0$
#955
b1011 +
1"
b10100010000000010010011 !
b10100010000000010010011 *
1%
1$
#960
0$
#965
b1100 +
b101000100010001010010011 !
b101000100010001010010011 *
1$
#970
0$
#975
0"
0%
1$
#980
0$
#985
b11000 '
1$
#990
0$
#995
b1101 +
1"
b100110011001100010011 !
b100110011001100010011 *
1%
1$
#1000
0$
#1005
b1110 +
b111101000100001110010011 !
b111101000100001110010011 *
1$
#1010
0$
#1015
0"
0%
1$
#1020
0$
#1025
b11001 '
1$
#1030
0$
#1035
b1111 +
1"
b11111111111101010101011010010011 !
b11111111111101010101011010010011 *
1%
1$
#1040
0$
#1045
b10000 +
b11101100111011000010011 !
b11101100111011000010011 *
1$
#1050
0$
#1055
0"
0%
1$
#1060
0$
#1065
b11010 '
1$
#1070
0$
#1075
b10001 +
1"
b1011100101110110010011 !
b1011100101110110010011 *
1%
1$
#1080
0$
#1085
b10010 +
b1100001111100010010011 !
b1100001111100010010011 *
1$
#1090
0$
#1095
0"
0%
1$
#1100
0$
#1105
b11011 '
1$
#1110
0$
#1115
b10011 +
1"
b1000001000100101010000100010011 !
b1000001000100101010000100010011 *
1%
1$
#1120
0$
#1125
b10100 +
b1000000010000000000000011 !
b1000000010000000000000011 *
1$
#1130
0$
#1135
0"
0%
1$
#1140
0$
#1145
b11100 '
1$
#1150
0$
#1155
b10101 +
1"
b10000000100010000100000011 !
b10000000100010000100000011 *
1%
1$
#1160
0$
#1165
b10110 +
b100000000101010000100000011 !
b100000000101010000100000011 *
1$
#1170
0$
#1175
0"
0%
1$
#1180
0$
#1185
b11101 '
1$
#1190
0$
#1195
b10111 +
1"
b1000000000101011000110000011 !
b1000000000101011000110000011 *
1%
1$
#1200
0$
#1205
b11000 +
b100101010010100000100011 !
b100101010010100000100011 *
1$
#1210
0$
#1215
0"
0%
1$
#1220
0$
#1225
b11110 '
1$
